<?xml version="1.0" standalone="no"?>
<!DOCTYPE svg PUBLIC "-//W3C//DTD SVG 1.1//EN" "http://www.w3.org/Graphics/SVG/1.1/DTD/svg11.dtd" >
<svg xmlns="http://www.w3.org/2000/svg">
<metadata>
This is a custom SVG webfont generated by Font Squirrel.
Copyright   : C Copyright SoftUnion Ltd 1993 Created by NVsesvetskii
</metadata>
<defs>
<font id="RadarNormal" horiz-adv-x="512" >
<font-face units-per-em="2048" ascent="1638" descent="-410" />
<missing-glyph horiz-adv-x="368" />
<glyph unicode=" "  horiz-adv-x="368" />
<glyph unicode="&#x09;" horiz-adv-x="368" />
<glyph unicode="&#xa0;" horiz-adv-x="368" />
<glyph unicode="!" horiz-adv-x="233" d="M41 51q0 31 22.5 53.5t53.5 22.5t53.5 -22.5t22.5 -53.5t-23 -53.5t-53 -22.5q-31 0 -53.5 22.5t-22.5 53.07FA5ADAE1" />
<glyph unicode="&#x22;" horiz-adv-x="430" d="M41 1376q0 39 21.5 73t54.5 34t54.5 -34t21.5 -73q0 -20 -37 -123q-20 -57 -21 -120h-37q0 82 -28.5 145t-03F1EDAA97" />
<glyph unicode="#" horiz-adv-x="509" d="M20 0l113 637h-106l6 41h106l23 127h-107l8 41h107l109 612h40l-108 -612h127l111 612h40l-110 -612h110l-8 -41h-110l-23 -127h111l-6 -41h-111l-113 -637h-41l113 637h-127l-113 -637h-41zM180 678h127l23 127h-127z" />
<glyph unicode="$" horiz-adv-x="466" d="M37 1133q0 133 29 219q43 131 141 131v33h41v-37q23 -6 45 -23.5t26 -17.5q23 0 32 13t14 19h28v-493h-41q0 188 -12 272q-23 158 -92 189v-611q131 -258 153 -329q37 -115 37 -234q0 -104 -43 -186q-53 -102 -147 -103v-71h-41v78q-14 6 -39 22t-39 16q-20 0 -39 -28 h-41v514h41q0 -172 21 -287q29 -162 96 -196v632q-53 104 -88 179q-82 176 -82 299zM123 1276q0 -96 22.5 -184t61.5 -179v531q-43 -6 -63.5 -59.5t-20.5 -108.5zM248 12q49 0 76.5 41t27.5 152q0 90 -27.5 180t-76.5 190v-563z" />
<glyph unicode="%" horiz-adv-x="897" d="M41 1016v196q0 115 50 193t130 78q78 0 129 -78t51 -193v-196q0 -115 -50 -195t-130 -80q-78 0 -129 80t-51 195zM139 975q0 -197 82 -197t82 197v278q0 86 -22.5 139.5t-59.5 53.5t-59.5 -52.5t-22.5 -140.5v-278zM303 0l250 1458h41l-250 -1458h-41zM496 250v196 q0 115 50 193t130 78q78 0 129 -78t51 -193v-196q0 -115 -50 -195t-130 -80q-78 0 -129 80t-51 195zM594 209q0 -197 82 -197t82 197v278q0 86 -22.5 139.5t-59.5 53.5t-59.5 -52.5t-22.5 -140.5v-278z" />
<glyph unicode="&#x26;" horiz-adv-x="649" d="M37 360q0 119 34.5 218.5t104.5 203.5q-51 131 -63 172q-29 96 -29 195q0 119 47 219q55 115 137 115q84 004DAA35A27" />
<glyph unicode="'" horiz-adv-x="301" d="M39 1401q0 33 20.5 57.5t51.5 24.5q47 0 75.5 -35t28.5 -88q0 -70 -46 -126t-112 -56q-10 0 -10 14q0 18 10E2EAC7AE6" />
<glyph unicode="(" horiz-adv-x="348" d="M119 147v922q0 190 52 320.5t136 130.5v-37q-37 0 -61.5 -99.5t-24.5 -242.5v-1065q0 -158 23.5 -248t62.5 -90v-37q-84 0 -136 128t-52 318z" />
<glyph unicode=")" horiz-adv-x="348" d="M41 -262q37 0 61.5 92t24.5 246v1065q0 147 -23.5 244.5t-62.5 97.5v37q84 0 136 -129t52 -322v-922q0 -190 -52 -318t-136 -128v37z" />
<glyph unicode="*" horiz-adv-x="706" d="M41 1001q0 53 42 78t116.5 32t101.5 17q-33 12 -108.5 21.5t-108.5 28.5q-43 29 -43 77q0 18 10 43q23 43 78 43q23 0 45 -12q35 -20 64 -57q78 -102 96 -115q0 45 -35 121t-35 115q0 37 26.5 63.5t61.5 26.5t61.5 -26.5t26.5 -63.5q0 -35 -47 -144q-23 -51 -22 -92 q80 86 161 172q23 12 46 12q47 0 73 -43q12 -23 13 -47q0 -51 -40 -74.5t-116 -30.5t-107 -20q35 -12 111 -21t114 -30.5t38 -75.5q0 -27 -11 -43q-23 -43 -75 -43q-25 0 -48 13q-33 18 -63 57q-80 100 -94 113l65 -217q0 -35 -26.5 -61.5t-61.5 -26.5t-61.5 26.5 t-26.5 63.5t19 82q49 119 51 135q-80 -86 -158 -170q-23 -12 -45 -13q-47 0 -76 46q-12 17 -12 40z" />
<glyph unicode="+" horiz-adv-x="569" d="M41 602v53h217v217h53v-217h217v-53h-217v-217h-53v217h-217z" />
<glyph unicode="," horiz-adv-x="301" d="M39 45q0 33 20.5 57.5t51.5 24.5q47 0 75.5 -35t28.5 -88q0 -70 -46 -126t-112 -56q-10 0 -10 14q0 18 10 0627E0AA5B" />
<glyph unicode="-" horiz-adv-x="325" d="M41 508v86h244v-86h-244z" />
<glyph unicode="." horiz-adv-x="233" d="M41 51q0 31 22.5 53.5t53.5 22.5t53.5 -22.5t22.5 -53.5t-23 -53.5t-53 -22.5q-31 0 -53.5 22.5t-22.5 53.5z" />
<glyph unicode="../../../default.htm" horiz-adv-x="321" d="M20 0l250 1458h41l-250 -1458h-41z" />
<glyph unicode="0" d="M35 524v394q0 231 63.5 398t161.5 167q96 0 160.5 -168t64.5 -397v-394q0 -229 -63.5 -389t-161.5 -160q-96 0 -160.5 161t-64.5 388zM158 442q0 -197 27.5 -313.5t74.5 -116.5q45 0 73.5 119t28.5 311v557q0 184 -27.5 315.5t-74.5 131.5q-43 0 -72.5 -133t-29.5 -314 v-557z" />
<glyph unicode="1" d="M109 924q113 281 112 534h123v-1421h98v-37h-319v37h98v1087q-16 -63 -35.5 -115.5t-44.5 -101.5z" />
<glyph unicode="2" d="M61 0v100q0 162 68 363q61 170 128 359.5t67 351.5q0 106 -11 169q-16 102 -59 103q-66 0 -107 -79t-41 -163q0 -29 3.5 -48t17.5 -19q16 8 35 8q49 0 49 -64q0 -39 -17.5 -60.5t-60.5 -21.5t-57.5 49.5t-14.5 112.5q0 121 45 211q55 111 156 111q106 0 160 -109 q41 -84 41 -200q0 -162 -85 -347.5t-165 -353.5q-90 -203 -90 -354h215q35 0 43 19.5t8 51.5v121h49v-311h-377z" />
<glyph unicode="3" d="M49 229q0 74 36 139.5t105 65.5q33 0 47.5 -20.5t14.5 -53.5q0 -39 -18.5 -61.5t-57.5 -22.5q-8 0 -23.5 13.5t-25.5 13.5q-18 0 -25.5 -27.5t-7.5 -62.5v-20q0 -68 32 -124.5t93 -56.5q53 0 86 56.5t33 117.5v349q0 137 -14 184q-20 68 -86 67h-64v37h64q39 0 59 65.5 t20 131.5v295q0 49 -20.5 90t-56.5 41q-47 0 -84 -76t-37 -137q0 -18 6 -32.5t16 -14.5q16 0 26 3l21 7q25 0 41.5 -14.5t16.5 -44.5q0 -84 -86 -84q-53 0 -74 63q-12 39 -12 109q0 86 48 172t124 86q115 0 164 -127q35 -90 34 -230q0 -106 -38.5 -200.5t-106.5 -118.5 q88 -27 133 -152q37 -100 37 -227q0 -170 -51 -291q-70 -162 -209 -162q-90 0 -129 86q-31 66 -31 168z" />
<glyph unicode="4" d="M23 358q25 184 73 406q43 180 87 372.5t57 321.5h122v-1063h123v-37h-123v-321h99v-37h-320v37h99v321h-217zM68 395h172v735q-78 -281 -95 -342q-46 -186 -77 -393z" />
<glyph unicode="5" d="M43 211q0 88 18 139q27 76 95 76q27 0 48 -17.5t21 -46.5q0 -76 -49 -75q-18 0 -34.5 6t-22.5 6q-14 0 -22.5 -37t-8.5 -72q0 -66 27 -114q35 -63 90 -64q61 0 94 46t33 180v57v354q0 90 -13 142q-20 80 -67 79q-35 0 -63.5 -22.5t-41.5 -61.5h-32v672h309v-256h-37v64 q0 27 -15.5 47t-47.5 20h-160v-454q16 16 42.5 28.5t55.5 12.5q121 0 168 -152q29 -94 29 -256q0 -217 -39 -342q-61 -195 -217 -195q-72 0 -116 77t-44 159z" />
<glyph unicode="6" d="M33 455v186q0 170 18 322q27 223 84 354q72 166 187 166q55 0 89.5 -54.5t34.5 -113.5q0 -57 -20 -101q-270FBD749A16" />
<glyph unicode="7" d="M102 1163v295h381q-127 -389 -188 -702q-72 -362 -72 -697q0 -72 -65 -71q-27 0 -43.5 20.5t-10.5 50.5q27 207 76 441q37 174 105 436q55 215 112 403h-176q-37 0 -52 -48t-15 -128h-52z" />
<glyph unicode="8" d="M35 383q0 158 46 292t109 152q-57 12 -89.5 110.5t-32.5 201.5q0 143 41 233q49 111 147 111q82 0 135 -102.5t53 -237.5q0 -115 -28.5 -209t-87.5 -107q63 -16 106 -129.5t43 -275.5q0 -182 -49 -303q-59 -143 -172 -144q-92 0 -156.5 125t-64.5 283zM162 205 q0 -76 16 -123q25 -70 78 -70t78 72q16 49 16 121v358q0 66 -24 146q-31 96 -70 96q-43 0 -68.5 -79t-25.5 -163v-358zM186 991q0 -59 20.5 -104t49.5 -45t49.5 43t20.5 106v307q0 61 -20.5 104.5t-49.5 43.5t-49.5 -43t-20.5 -105v-307z" />
<glyph unicode="9" d="M35 987q0 254 71 385q61 111 166 111q117 0 168 -185q35 -125 35 -313v-186q0 -168 -16 -318q-25 -219 -78 -344q-70 -162 -182 -162q-59 0 -93 63.5t-34 125.5q0 57 23.5 107.5t76.5 50.5q68 0 68 -74q0 -29 -22.5 -49.5t-53.5 -20.5q-47 0 -47 -43q0 -41 20.5 -82 t59.5 -41q76 0 116 224q35 186 35 419q-14 -35 -45 -59.5t-63 -24.5q-104 0 -160 136q-45 110 -45 280zM154 1010q0 -154 12 -248q20 -150 65 -150q63 0 95 154q23 113 22 250q0 186 -10 264q-23 166 -86 166q-70 0 -90 -238q-8 -96 -8 -198z" />
<glyph unicode=":" horiz-adv-x="233" d="M41 51q0 31 22.5 53.5t53.5 22.5t53.5 -22.5t22.5 -53.5t-23 -53.5t-53 -22.5q-31 0 -53.5 22.5t-22.5 53.02B1B09A96" />
<glyph unicode=";" horiz-adv-x="249" d="M41 51q0 31 22.5 53.5t53.5 22.5t53.5 -22.5t22.5 -53.5t-23 -53.5t-53 -22.5q-31 0 -53.5 22.5t-22.5 53.0548968ADC" />
<glyph unicode="&#x3c;" horiz-adv-x="569" d="M41 596v63l461 267l26 -47l-432 -250l432 -252l-26 -47z" />
<glyph unicode="=" horiz-adv-x="569" d="M41 532v54h487v-54h-487zM41 676v53h487v-53h-487z" />
<glyph unicode="&#x3e;" horiz-adv-x="569" d="M41 377l432 252l-432 250l27 47l460 -267v-63l-460 -266z" />
<glyph unicode="?" horiz-adv-x="475" d="M20 1137q0 125 46 223q55 123 155 123q106 0 160 -121q41 -92 41 -213q0 -162 -43 -294t-84 -253q-47 -16208FA58CAFB" />
<glyph unicode="@" horiz-adv-x="710" d="M29 477q0 516 75.5 761t241.5 245q168 0 244 -231.5t76 -774.5q0 -195 -21 -297q-39 -193 -147 -192q-43 00395C7AA65" />
<glyph unicode="A" horiz-adv-x="581" d="M0 0v37h61l201 1446h49l193 -1446h67v-37h-256v37h62l-70 471h-127l-65 -471h61v-37h-176zM182 545h121l-55 454z" />
<glyph unicode="B" horiz-adv-x="571" d="M20 0v37h99v1384h-84v37h219q147 0 207 -110q45 -84 45 -244q0 -123 -31 -211q-39 -113 -119 -131q78 -12 128.5 -124t50.5 -247q0 -164 -39 -254q-59 -137 -213 -137h-263zM242 37h47q66 0 96 123q23 90 23 229q0 141 -25 227q-37 129 -121 129h-20v-708zM242 782h18 q68 0 102 125q25 90 25 201q0 113 -25 197q-35 117 -106 116h-14v-639z" />
<glyph unicode="C" horiz-adv-x="487" d="M41 629v207q0 303 45 458q55 188 180 189q33 0 58.5 -17.5t54.5 -35.5q25 0 33 28h37v-551h-37q0 190 -31 344q-39 195 -111 195q-80 0 -98 -156q-8 -72 -8 -160v-794q0 -129 16 -207q25 -117 86 -117q70 0 108 188.5t38 512.5h37q0 -362 -39 -537q-45 -201 -144 -201 q-129 0 -182 191q-43 154 -43 463z" />
<glyph unicode="D" horiz-adv-x="567" d="M20 0v37h99v1384h-84v37h207q160 0 235 -188q59 -150 60 -398v-286q0 -195 -76 -375q-88 -211 -219 -211h-222zM242 37h20q72 0 115 125q37 109 37 248v639q0 186 -32 279t-103 93h-37v-1384z" />
<glyph unicode="E" d="M20 0v37h99v1384h-84v37h428v-430h-37q0 166 -14 248q-27 145 -97 145h-73v-659h41q49 0 65.5 67.5t16.5 194.5h36v-561h-36q0 135 -13 186q-18 76 -69 76h-41v-688h63q141 0 141 461h37v-498h-463z" />
<glyph unicode="F" horiz-adv-x="483" d="M20 0v37h99v1384h-84v37h428v-430h-37q0 166 -14 248q-27 145 -97 145h-73v-659h41q49 0 65.5 67.5t16.5 194.5h36v-561h-36q0 135 -13 186q-18 76 -69 76h-41v-688h98v-37h-320z" />
<glyph unicode="G" horiz-adv-x="536" d="M37 629v207q0 303 45 458q55 188 180 189q33 0 58.5 -17.5t54.5 -35.5q25 0 33 28h36v-551h-36q0 190 -31 344q-39 195 -111 195q-80 0 -98 -156q-8 -72 -8 -160v-794q0 -129 16 -207q25 -117 86 -117q35 0 57.5 53.5t22.5 114.5v531h-61v37h245v-37h-61v-691h-21l-61 58 q-16 -45 -47 -74t-74 -29q-129 0 -182 191q-43 154 -43 463z" />
<glyph unicode="H" horiz-adv-x="638" d="M20 0v37h99v1384h-84v37h268v-37h-61v-659h155v659h-61v37h282v-37h-98v-1384h98v-37h-282v37h61v688h-155v-688h61v-37h-283z" />
<glyph unicode="I" horiz-adv-x="360" d="M20 0v37h99v1384h-99v37h320v-37h-98v-1384h98v-37h-320z" />
<glyph unicode="J" horiz-adv-x="501" d="M20 -10v465h37q0 -236 41 -349q35 -94 97 -94q49 0 65 56q10 33 10 104v1249h-98v37h320v-37h-99v-1138q0 -121 -41 -203q-53 -104 -157 -105q-35 0 -68 26t-41 26q-6 0 -16.5 -12.5t-12.5 -24.5h-37z" />
<glyph unicode="K" horiz-adv-x="630" d="M20 0v37h99v1384h-99v37h320v-37h-98v-647l207 647h-62v37h174v-37h-61l-178 -561l241 -823h62v-37h-179l-184 672l-20 -66v-569h98v-37h-320z" />
<glyph unicode="L" horiz-adv-x="503" d="M20 0v37h99v1384h-99v37h320v-37h-98v-1384h63q141 0 141 461h37v-498h-463z" />
<glyph unicode="M" horiz-adv-x="837" d="M10 0v37h99v1384h-84v37h206l187 -1028l178 1028h221v-37h-98v-1384h98v-37h-319v37h98v1175l-199 -1185h-24l-219 1185l-4 -1175h98v-37h-238z" />
<glyph unicode="N" horiz-adv-x="587" d="M20 1421v37h199l225 -885l7 848h-62v37h182v-37h-79v-1421h-29l-291 1219l-4 -1182h98v-37h-237v37h98v1384h-107z" />
<glyph unicode="O" horiz-adv-x="524" d="M37 631v180q0 293 56.5 482.5t168.5 189.5q111 0 168 -190.5t57 -481.5v-180q0 -313 -41 -463q-53 -193 -184 -193q-129 0 -182 191q-43 154 -43 465zM160 352q0 -135 16 -215q25 -125 86 -125t86 125q16 82 17 215v754q0 162 -11 219q-23 121 -92 121q-68 0 -90 -121 q-12 -68 -12 -219v-754z" />
<glyph unicode="P" horiz-adv-x="548" d="M20 0v37h99v1384h-84v37h244q117 0 180 -112.5t63 -278.5q0 -162 -67.5 -276.5t-163.5 -114.5h-49v37h37q47 0 83.5 70.5t36.5 166.5v217q0 109 -28.5 181.5t-91.5 72.5h-37v-1384h98v-37h-320z" />
<glyph unicode="Q" horiz-adv-x="524" d="M37 631v155q0 311 45 484q55 213 180 213q123 0 178 -211q47 -178 47 -486v-155q0 -254 -28 -402q-35 -178 -117 -231l90 -123l-41 -31l-86 138l-43 -7q-129 0 -182 191q-43 154 -43 465zM160 336q0 -137 28.5 -230.5t73.5 -93.5l21 4l-45 74l26 19l49 -70 q31 41 41.5 120t10.5 177v745q0 152 -15 232q-25 133 -88 133q-76 0 -94 -191q-8 -84 -8 -174v-745z" />
<glyph unicode="R" horiz-adv-x="628" d="M20 0v37h99v1384h-84v37h246q254 0 254 -371q0 -135 -37 -217t-101 -125l170 -708h62v-37h-170l-164 709h-53v-672h98v-37h-320zM242 745h37q57 0 96 67t39 171v191q0 113 -33 180t-100 67h-39v-676z" />
<glyph unicode="S" horiz-adv-x="462" d="M31 1133q0 133 30 221q45 129 148 129q33 0 56.5 -14.5t47.5 -30.5q23 0 32 13t13 19h29v-493h-41q0 207 -16 299q-31 170 -121 170q-47 0 -69.5 -56.5t-22.5 -113.5q0 -172 82 -358q76 -154 154.5 -322t78.5 -332q0 -109 -43 -188q-55 -100 -156 -101q-27 0 -71 31 q-20 14 -39 14q-20 0 -39 -28h-41v514h41q0 -195 27 -318q39 -176 127 -176q63 0 90 64q18 45 18 129q0 143 -82 323q-76 150 -151 301q-82 175 -82 304z" />
<glyph unicode="T" horiz-adv-x="516" d="M20 979v479h476v-479h-37q0 193 -15 283q-27 160 -96 159h-29v-1384h99v-37h-320v37h99v1384h-29q-82 0 -102 -227q-8 -94 -9 -215h-37z" />
<glyph unicode="U" horiz-adv-x="526" d="M10 1421v37h283v-37h-62v-1298q0 -47 25 -79t61 -32q39 0 68 33t29 80v1296h-62v37h164v-37h-61v-1288q0 -66 -44 -112t-110 -46q-80 0 -136 48.5t-56 117.5v1280h-99z" />
<glyph unicode="V" horiz-adv-x="528" d="M10 1421v37h242v-37h-62l97 -889l129 889h-84v37h196v-37h-61l-203 -1446h-37l-155 1446h-62z" />
<glyph unicode="W" horiz-adv-x="813" d="M10 1421v37h242v-37h-62l89 -905l147 942h25l116 -942l125 905h-61v37h182v-37h-80l-203 -1446h-24l-117 959l-147 -959h-25l-145 1446h-62z" />
<glyph unicode="X" horiz-adv-x="573" d="M20 1421v37h242v-37h-61l98 -483l90 483h-61v37h182v-37h-80l-102 -596l159 -788h86v-37h-270v37h62l-111 512l-96 -512h61v-37h-182v37h80l108 653l-143 731h-62z" />
<glyph unicode="Y" horiz-adv-x="530" d="M29 1421v37h241v-37h-61l102 -700l99 700h-62v37h182v-37h-79l-109 -807v-577h98v-37h-319v37h98v557l-129 827h-61z" />
<glyph unicode="Z" horiz-adv-x="528" d="M41 0v37l321 1384h-141q-90 0 -123 -131q-20 -80 -20 -246h-37v414h459v-37l-303 -1384h100q80 0 110.5 88t30.5 324h37v-449h-434z" />
<glyph unicode="[" horiz-adv-x="301" d="M102 -299v1819h199v-37h-84v-1745h84v-37h-199z" />
<glyph unicode="\" horiz-adv-x="321" d="M20 1458h41l250 -1458h-41z" />
<glyph unicode="]" horiz-adv-x="301" d="M20 -262h84v1745h-84v37h199v-1819h-199v37z" />
<glyph unicode="^" horiz-adv-x="636" d="M20 446l267 461h63l266 -461l-47 -26l-250 432l-251 -432z" />
<glyph unicode="_" horiz-adv-x="684" d="M0 -528h684v-54h-684v54z" />
<glyph unicode="`" horiz-adv-x="301" d="M35 1276q0 70 46 126t112 56q10 0 10 -14q0 -18 -10 -19q-31 0 -72 -38.5t-41 -71.5q0 -35 16 -35q8 0 28.05E35FAA0D" />
<glyph unicode="a" d="M37 233q0 133 31 209q41 102 143 103q12 0 29.5 -7.5t29.5 -19.5v293q0 27 -13 49.5t-40 22.5q-31 0 -67.50C8188AA08" />
<glyph unicode="b" horiz-adv-x="487" d="M10 1421v37h199v-602q18 33 39.5 48.5t50.5 15.5q90 0 125 -172q23 -109 22 -261q0 -252 -39.5 -375.5t-119.5 -123.5q-27 0 -43.5 16t-30.5 45l-4 -49h-176v37h61v1384h-84zM209 195q0 -55 21.5 -106.5t41.5 -51.5q29 0 42.5 65.5t13.5 135.5v450q0 80 -14.5 131 t-39.5 51q-23 0 -44 -66.5t-21 -162.5v-446z" />
<glyph unicode="c" horiz-adv-x="385" d="M41 434q0 170 39 307q51 178 141 179q16 0 39 -12.5t33 -12.5q18 0 18 25h37v-336h-37q0 121 -26.5 210t-59.5 89q-66 0 -65 -201v-530q0 -115 55 -115q45 0 70.5 119.5t25.5 296.5h37q0 -215 -29 -324q-37 -141 -126 -141q-80 0 -116 128t-36 318z" />
<glyph unicode="d" horiz-adv-x="479" d="M37 461q0 184 24 284q43 174 158 175q41 0 60 -41l4 542h-84v37h198v-1421h62v-37h-176v47q-14 -25 -35 -42t-53 -17q-78 0 -118 118.5t-40 354.5zM156 465q0 -217 12 -322.5t57 -105.5q39 0 51 84q6 43 7 162v346q0 123 -13.5 182t-44.5 59q-45 0 -57 -100t-12 -305z " />
<glyph unicode="e" horiz-adv-x="432" d="M41 438q0 213 29 320q43 162 159 162q72 0 113 -93q53 -119 53 -335h-235v-314q0 -78 18.5 -109.5t48.5 -3070E6FFACA" />
<glyph unicode="f" horiz-adv-x="307" d="M20 870v37h74v361q0 84 39 143q47 72 133 72q55 0 92 -31t37 -84q0 -57 -14 -94q-20 -53 -70 -53q-27 0 -48 19.5t-21 53.5q0 43 16 59.5t39 16.5q20 -8 29 -8q20 0 20 22q0 18 -19.5 40t-45.5 22q-45 0 -58.5 -51.5t-13.5 -124.5v-363h74v-37h-74v-833h61v-37h-237v37 h61v833h-74z" />
<glyph unicode="g" horiz-adv-x="479" d="M4 -428q0 51 32 85t77 34q27 0 46 -19.5t19 -48.5t-17.5 -50.5t-41.5 -21.5q-8 0 -24.5 6.5t-22.5 6.5q-18 0 -19 -37q0 -29 29 -47.5t61 -18.5q92 0 123 123q16 66 17 209v254q-14 -25 -35 -42t-53 -17q-78 0 -118 118.5t-40 354.5q0 184 24 284q43 174 158 175 q41 0 60 -41l4 28h176v-37h-62v-1077q0 -156 -72.5 -262t-187.5 -106q-63 0 -98 38.5t-35 108.5zM156 465q0 -217 12 -322.5t57 -105.5q39 0 51 84q6 43 7 162v346q0 123 -13.5 182t-44.5 59q-45 0 -57 -100t-12 -305z" />
<glyph unicode="h" horiz-adv-x="530" d="M10 1421v37h199v-584q20 23 53 34.5t57 11.5q57 0 93.5 -50.5t36.5 -121.5v-711h61v-37h-176v795q0 76 -45 75q-23 0 -49.5 -28.5t-30.5 -57.5v-747h61v-37h-237v37h61v1384h-84z" />
<glyph unicode="i" horiz-adv-x="301" d="M20 870v37h199v-870h62v-37h-238v37h61v833h-84zM86 1124q0 31 22.5 53.5t53.5 22.5t53.5 -22.5t22.5 -53.5t-22.5 -53t-53.5 -22t-53.5 22t-22.5 53z" />
<glyph unicode="j" horiz-adv-x="284" d="M-168 -428q0 51 32 85t77 34q27 0 46 -19.5t19 -48.5t-17.5 -50.5t-41.5 -21.5q-8 0 -24.5 6.5t-22.5 6.5q0F99543AB6" />
<glyph unicode="k" horiz-adv-x="548" d="M10 1421v37h199v-975l192 387h-61v37h182v-37h-80l-139 -274l184 -559h62v-37h-166l-143 465l-31 -57v-371h61v-37h-237v37h61v1384h-84z" />
<glyph unicode="l" horiz-adv-x="290" d="M10 1421v37h199v-1421h61v-37h-237v37h61v1384h-84z" />
<glyph unicode="m" horiz-adv-x="778" d="M20 870v37h199v-47q25 25 49 39q35 20 70 21q41 0 74 -27q25 -20 45 -57q23 37 55.5 60.5t67.5 23.5q53 0 90 -39t37 -103v-741h61v-37h-176v817q0 53 -35 53q-31 0 -54.5 -28.5t-39.5 -75.5v-729h61v-37h-176v817q0 53 -35 53q-31 0 -54 -28.5t-40 -75.5v-729h62v-37 h-238v37h61v833h-84z" />
<glyph unicode="n" horiz-adv-x="534" d="M20 870v37h199v-47q43 59 115 60q53 0 91 -45.5t38 -104.5v-733h61v-37h-176v817q0 53 -35 53q-31 0 -54 -28.5t-40 -75.5v-729h62v-37h-238v37h61v833h-84z" />
<glyph unicode="o" horiz-adv-x="454" d="M41 471q0 182 37 299q47 150 149 150t150 -148q37 -117 37 -303q0 -193 -35 -313q-49 -168 -152 -168q-100 0 -149 168q-37 127 -37 315zM160 182q0 -72 8 -100q16 -57 59 -57q49 0 62 81q6 39 6 78v496q0 84 -10 129q-16 74 -58 74q-47 0 -61 -105q-6 -47 -6 -98v-498z " />
<glyph unicode="p" horiz-adv-x="487" d="M10 870v37h199v-51q18 33 39.5 48.5t50.5 15.5q90 0 125 -172q23 -109 22 -261q0 -252 -39.5 -375.5t-119.5 -123.5q-27 0 -43.5 16t-30.5 45l-4 -575h61v-37h-237v37h61v1396h-84zM209 195q0 -55 21.5 -106.5t41.5 -51.5q29 0 42.5 65.5t13.5 135.5v450q0 80 -14.5 131 t-39.5 51q-23 0 -44 -66.5t-21 -162.5v-446z" />
<glyph unicode="q" horiz-adv-x="497" d="M41 487q0 160 20 258q37 174 127 175q55 0 84 -64l7 51h198v-37h-84v-1396h62v-37h-238v37h62v575q-18 -29 -31 -41q-20 -20 -47 -20q-78 0 -119 125.5t-41 373.5zM160 238q0 -76 12 -138.5t43 -62.5q20 0 42 49t22 109v446q0 100 -20.5 164.5t-45.5 64.5t-39 -51 t-14 -131v-450z" />
<glyph unicode="r" horiz-adv-x="411" d="M20 870v37h199v-80q25 43 47 64q31 29 70 29q74 0 74 -76q0 -39 -19.5 -70t-52.5 -31q-29 0 -43 52q-6 25 -21 24q-25 0 -40 -60.5t-15 -121.5v-600h62v-37h-238v37h61v833h-84z" />
<glyph unicode="s" horiz-adv-x="380" d="M37 0v383h37q0 -213 30 -293q25 -66 76 -65q45 0 66 47q14 35 14 92q0 86 -145 340q-70 121 -70 217q0 82 29 133q37 66 112 66q14 0 35 -9q45 -18 51 -18q18 0 25 27h37v-361h-37q0 174 -32 249t-83 75q-37 0 -51 -26t-14 -73q0 -100 111.5 -272t111.5 -279 q0 -92 -33 -159q-43 -86 -125 -86q-18 0 -42.5 14t-39.5 14q-16 0 -26 -16h-37z" />
<glyph unicode="t" horiz-adv-x="315" d="M20 870v37h58v318l115 24v-342h102v-37h-102v-798q0 -35 34 -35q31 0 31 35v354h37v-344q0 -39 -29.5 -66.5t-72.5 -27.5q-53 0 -84 48t-31 97v737h-58z" />
<glyph unicode="u" horiz-adv-x="522" d="M20 870v37h177v-815q0 -33 14 -44t35 -11q27 0 53.5 53t26.5 105v675h-62v37h176v-870h62v-37h-176v53q-25 -37 -50.5 -51t-58.5 -14q-63 0 -99 64.5t-36 170.5v647h-62z" />
<glyph unicode="v" horiz-adv-x="446" d="M10 870v37h238v-37h-62l74 -544l94 544h-61v37h164v-37h-62l-159 -882h-37l-127 882h-62z" />
<glyph unicode="w" horiz-adv-x="681" d="M10 870v37h238v-37h-62l72 -522l115 559h39l77 -559l101 522h-62v37h164v-37h-61l-166 -882h-37l-78 530l-123 -530h-37l-118 882h-62z" />
<glyph unicode="x" horiz-adv-x="466" d="M20 0v37h62l115 385l-119 448h-58v37h216v-37h-43l63 -249l80 249h-45v37h147v-37h-61l-101 -344l123 -489h47v-37h-210v37h61l-78 313l-92 -313h45v-37h-152z" />
<glyph unicode="y" horiz-adv-x="456" d="M-47 -496q0 27 18.5 45.5t44.5 18.5q31 0 45.5 -35t24.5 -35q14 0 31.5 34t25.5 95l56 373l-131 870h-62v3066CAC0A27" />
<glyph unicode="z" horiz-adv-x="407" d="M33 0v37l246 833h-80q-68 0 -97 -94q-20 -68 -20 -196h-37v327h340v-37l-240 -833h64q68 0 96 121q20 84 21 207h36v-365h-329z" />
<glyph unicode="{" horiz-adv-x="348" d="M27 612v37h30q25 0 43.5 20.5t18.5 49.5v596q0 82 55 143.5t133 61.5v-37q-37 0 -61.5 -29t-24.5 -70v-628q0 -47 -22.5 -84t-55.5 -43q33 -6 55.5 -43t22.5 -84v-670q0 -41 24.5 -67.5t61.5 -26.5v-37q-80 0 -134 58.5t-54 142.5v641q0 31 -17.5 50t-44.5 19h-30z" />
<glyph unicode="|" horiz-adv-x="245" d="M102 -563v2021h41v-2021h-41z" />
<glyph unicode="}" horiz-adv-x="348" d="M25 -262q37 0 61.5 26.5t24.5 67.5v670q0 43 20.5 81t48.5 46q-29 10 -49 46t-20 81v628q0 39 -26 69t-60 07F018AA81" />
<glyph unicode="~" horiz-adv-x="600" d="M41 537q0 66 41 110.5t102 44.5q33 0 135 -35q53 -18 82 -18q39 0 67 15.5t28 37.5h36q0 -156 -178 -155q-29 0 -75 16q-106 37 -132 37q-29 0 -49 -13.5t-20 -39.5h-37z" />
<glyph unicode="&#xa1;" horiz-adv-x="233" d="M39 844q0 31 22.5 53.5t53.5 22.5t53 -23t22 -53q0 -31 -22.5 -53.5t-52.5 -22.5q-31 0 -53.5 22.5t-22.5 0D5BD07AAB" />
<glyph unicode="&#x40e;" horiz-adv-x="233" d="M39 844q0 31 22.5 53.5t53.5 22.5t53 -23t22 -53q0 -31 -22.5 -53.5t-52.5 -22.5q-31 0 -53.5 22.5t-22.5 0D5BD07AAB" />
<glyph unicode="&#xa2;" horiz-adv-x="380" d="M37 434q0 160 35 293q45 172 125 193v118h41v-118q25 -12 51 -25q18 0 18 25h37v-336h-37q0 121 -26.5 21006436D4A7D " />
<glyph unicode="&#x45e;" horiz-adv-x="380" d="M37 434q0 160 35 293q45 172 125 193v118h41v-118q25 -12 51 -25q18 0 18 25h37v-336h-37q0 121 -26.5 21006436D4A7D " />
<glyph unicode="&#xa3;" horiz-adv-x="524" d="M20 0v37h72q39 170 52.5 313.5t13.5 317.5h-138v45h138q0 84 -43 272q-20 90 -21 148q0 119 47 221q59 129 164 129q33 0 55 -10q23 -14 48 -27q29 0 38 37h37v-506h-37q0 193 -20 299q-33 170 -121 170q-49 0 -87 -61.5t-38 -112.5q0 -94 68 -342q33 -119 33 -217h165 v-45h-165q0 -186 -14.5 -327.5t-51.5 -303.5h90q141 0 141 461h37v-498h-463z" />
<glyph unicode="&#x408;" horiz-adv-x="524" d="M20 0v37h72q39 170 52.5 313.5t13.5 317.5h-138v45h138q0 84 -43 272q-20 90 -21 148q0 119 47 221q59 129 164 129q33 0 55 -10q23 -14 48 -27q29 0 38 37h37v-506h-37q0 193 -20 299q-33 170 -121 170q-49 0 -87 -61.5t-38 -112.5q0 -94 68 -342q33 -119 33 -217h165 v-45h-165q0 -186 -14.5 -327.5t-51.5 -303.5h90q141 0 141 461h37v-498h-463z" />
<glyph unicode="&#xa5;" horiz-adv-x="530" d="M29 1421v37h241v-37h-61l96 -661h17l88 661h-62v37h182v-37h-79l-89 -661h138v-45h-144l-12 -86h156v-45h-158v-547h98v-37h-319v37h98v547h-158v45h152l-12 86h-140v45h132l-103 661h-61z" />
<glyph unicode="&#x490;" horiz-adv-x="530" d="M29 1421v37h241v-37h-61l96 -661h17l88 661h-62v37h182v-37h-79l-89 -661h138v-45h-144l-12 -86h156v-45h-158v-547h98v-37h-319v37h98v547h-158v45h152l-12 86h-140v45h132l-103 661h-61z" />
<glyph unicode="&#xa8;" d="M20 0v37h99v1384h-84v37h428v-430h-37q0 166 -14 248q-27 145 -97 145h-73v-659h41q49 0 65.5 67.5t16.5 10C69408A65" />
<glyph unicode="&#x401;" d="M20 0v37h99v1384h-84v37h428v-430h-37q0 166 -14 248q-27 145 -97 145h-73v-659h41q49 0 65.5 67.5t16.5 10C69408A65" />
<glyph unicode="&#xa9;" horiz-adv-x="1589" d="M41 729q0 311 221 532.5t533 221.5q311 0 532 -221.5t221 -532.5t-221 -532.5t-532 -221.5t-532.5 221.5t-221.5 532.5zM78 729q0 -297 210 -507t507 -210t506.5 210t209.5 507t-209.5 507t-506.5 210t-507 -210t-210 -507zM557 639v168q0 246 45 373q53 152 180 151 q35 0 59.5 -14t53.5 -29q14 0 20.5 11.5t12.5 31.5h37v-467h-37q0 152 -31 275q-39 156 -111 155q-70 0 -92 -84q-14 -51 -14 -166v-643q0 -102 16 -161q25 -92 86 -93q70 0 108 149.5t38 412.5h37q0 -293 -39 -435q-45 -164 -144 -163q-129 0 -182 153q-43 125 -43 375z " />
<glyph unicode="&#xaa;" horiz-adv-x="483" d="M61 1057q0 84 25 131q33 63 115 63q23 0 47 -16v162q0 49 -47 49q-33 0 -55.5 -16.5t-22.5 -40.5q0 -8 4 -0FD46C7AAC" />
<glyph unicode="&#x404;" horiz-adv-x="483" d="M61 1057q0 84 25 131q33 63 115 63q23 0 47 -16v162q0 49 -47 49q-33 0 -55.5 -16.5t-22.5 -40.5q0 -8 4 -0FD46C7AAC" />
<glyph unicode="&#xab;" horiz-adv-x="444" d="M41 225v64l164 219l35 -29l-144 -221l144 -225l-35 -33zM205 225v64l164 219l34 -29l-143 -221l143 -225l-34 -33z" />
<glyph unicode="&#xad;" horiz-adv-x="325" d="M41 508v86h244v-86h-244z" />
<glyph unicode="&#xae;" horiz-adv-x="1589" d="M41 729q0 311 221 532.5t533 221.5q311 0 532 -221.5t221 -532.5t-221 -532.5t-532 -221.5t-532.5 221.5t-221.5 532.5zM78 729q0 -297 210 -507t507 -210t506.5 210t209.5 507t-209.5 507t-506.5 210t-507 -210t-210 -507zM522 152v36h99v1106h-84v37h245 q254 0 254 -299q0 -109 -35.5 -172t-101.5 -102l168 -570h63v-36h-169l-164 569h-54v-533h99v-36h-320zM743 758h37q57 0 96 52t39 138v154q0 90 -31.5 141t-101.5 51h-39v-536z" />
<glyph unicode="&#xb0;" horiz-adv-x="696" d="M61 1194q0 117 84 203t203 86t203 -84t84 -205q0 -119 -84 -203t-203 -84t-203 84t-84 203zM98 1194q0 -102 74 -176t176 -74t176 74t74 176t-72.5 177t-177.5 75q-102 0 -176 -74t-74 -178z" />
<glyph unicode="&#xb2;" horiz-adv-x="442" d="M61 741v52q0 96 104.5 264t104.5 270q0 119 -65 119q-45 0 -76 -28.5t-31 -74.5q0 -35 19 -34q6 0 13 9t15 9q18 0 28.5 -14.5t10.5 -30.5q0 -31 -18.5 -48t-42.5 -17q-33 0 -47.5 35.5t-14.5 68.5q0 68 43 115t107 47q72 0 121 -45t49 -111q0 -102 -138.5 -252.5 t-138.5 -234.5h179q45 0 45 45v45h37v-189h-304z" />
<glyph unicode="&#x406;" horiz-adv-x="442" d="M61 741v52q0 96 104.5 264t104.5 270q0 119 -65 119q-45 0 -76 -28.5t-31 -74.5q0 -35 19 -34q6 0 13 9t15 9q18 0 28.5 -14.5t10.5 -30.5q0 -31 -18.5 -48t-42.5 -17q-33 0 -47.5 35.5t-14.5 68.5q0 68 43 115t107 47q72 0 121 -45t49 -111q0 -102 -138.5 -252.5 t-138.5 -234.5h179q45 0 45 45v45h37v-189h-304z" />
<glyph unicode="&#xb3;" horiz-adv-x="415" d="M39 862q0 55 28.5 92t71.5 37q25 0 41.5 -16.5t16.5 -42.5q0 -25 -16.5 -41.5t-41.5 -16.5q-10 0 -22.5 9.5t-20.5 9.5q-20 0 -20 -31q0 -41 29.5 -68.5t70.5 -27.5q39 0 66.5 34t27.5 81v127q0 53 -4 67q-12 43 -76 43h-51v37h51q31 0 47.5 32t16.5 64v119 q0 33 -17.5 54.5t-43.5 21.5q-39 0 -68 -26.5t-29 -65.5q0 -18 19 -19q8 0 16 4q20 10 25 11q41 0 41 -43q0 -23 -15.5 -42.5t-46.5 -19.5t-53.5 32t-22.5 77q0 55 39 92t99 37q66 0 112.5 -51.5t46.5 -126.5q0 -55 -30.5 -104.5t-85.5 -61.5q72 -12 106 -72q29 -47 29 -113 q0 -92 -59.5 -158.5t-143.5 -66.5q-55 0 -94 39t-39 94z" />
<glyph unicode="&#x456;" horiz-adv-x="415" d="M39 862q0 55 28.5 92t71.5 37q25 0 41.5 -16.5t16.5 -42.5q0 -25 -16.5 -41.5t-41.5 -16.5q-10 0 -22.5 9.5t-20.5 9.5q-20 0 -20 -31q0 -41 29.5 -68.5t70.5 -27.5q39 0 66.5 34t27.5 81v127q0 53 -4 67q-12 43 -76 43h-51v37h51q31 0 47.5 32t16.5 64v119 q0 33 -17.5 54.5t-43.5 21.5q-39 0 -68 -26.5t-29 -65.5q0 -18 19 -19q8 0 16 4q20 10 25 11q41 0 41 -43q0 -23 -15.5 -42.5t-46.5 -19.5t-53.5 32t-22.5 77q0 55 39 92t99 37q66 0 112.5 -51.5t46.5 -126.5q0 -55 -30.5 -104.5t-85.5 -61.5q72 -12 106 -72q29 -47 29 -113 q0 -92 -59.5 -158.5t-143.5 -66.5q-55 0 -94 39t-39 94z" />
<glyph unicode="&#xb8;" horiz-adv-x="428" d="M37 438q0 213 29 320q43 162 159 162q72 0 113 -93q53 -119 53 -335h-235v-314q0 -78 18.5 -109.5t48.5 -31.5q68 0 103 137q29 113 28 260h37q0 -174 -31 -280q-47 -166 -163 -166q-96 0 -136 168q-24 106 -24 282zM45 1124q0 31 22.5 53.5t53.5 22.5t53.5 -22.5 t22.5 -53.5t-22.5 -53t-53.5 -22t-53.5 22t-22.5 53zM156 528h120v82q0 100 -6 154q-14 119 -53 119t-50 -94.5t-11 -260.5zM236 1124q0 31 22.5 53.5t52.5 22.5q31 0 53.5 -22.5t22.5 -53.5t-22.5 -53t-53.5 -22t-53 22t-22 53z" />
<glyph unicode="&#x451;" horiz-adv-x="428" d="M37 438q0 213 29 320q43 162 159 162q72 0 113 -93q53 -119 53 -335h-235v-314q0 -78 18.5 -109.5t48.5 -31.5q68 0 103 137q29 113 28 260h37q0 -174 -31 -280q-47 -166 -163 -166q-96 0 -136 168q-24 106 -24 282zM45 1124q0 31 22.5 53.5t53.5 22.5t53.5 -22.5 t22.5 -53.5t-22.5 -53t-53.5 -22t-53.5 22t-22.5 53zM156 528h120v82q0 100 -6 154q-14 119 -53 119t-50 -94.5t-11 -260.5zM236 1124q0 31 22.5 53.5t52.5 22.5q31 0 53.5 -22.5t22.5 -53.5t-22.5 -53t-53.5 -22t-53 22t-22 53z" />
<glyph unicode="&#xba;" horiz-adv-x="407" d="M59 1204q0 113 31 185q41 94 123 94q84 0 123 -92q31 -72 31 -187q0 -113 -31 -192q-41 -104 -123 -105q-80 0 -121 105q-33 83 -33 192zM158 1028q0 -41 9 -62.5t46 -21.5q35 0 45 23.5t10 60.5v305q0 45 -10 79t-45 34t-45 -32t-10 -81v-305z" />
<glyph unicode="&#x454;" horiz-adv-x="407" d="M59 1204q0 113 31 185q41 94 123 94q84 0 123 -92q31 -72 31 -187q0 -113 -31 -192q-41 -104 -123 -105q-80 0 -121 105q-33 83 -33 192zM158 1028q0 -41 9 -62.5t46 -21.5q35 0 45 23.5t10 60.5v305q0 45 -10 79t-45 34t-45 -32t-10 -81v-305z" />
<glyph unicode="&#xbb;" horiz-adv-x="444" d="M41 33l35 -33l164 225v64l-164 219l-35 -29l143 -221zM205 33l35 -33l163 225v64l-163 219l-35 -29l143 -221z" />
<glyph unicode="&#xbc;" horiz-adv-x="913" d="M61 1192q41 63 66 134t25 132h98v-692h80v-37h-256v37h78v524q-12 -29 -21 -45q-16 -33 -41 -65zM301 0l250 1458h41l-250 -1458h-41zM481 178v37l172 514h99v-514h98v-37h-98v-141h79v-37h-256v37h78v141h-172zM518 215h135v397z" />
<glyph unicode="&#x458;" horiz-adv-x="913" d="M61 1192q41 63 66 134t25 132h98v-692h80v-37h-256v37h78v524q-12 -29 -21 -45q-16 -33 -41 -65zM301 0l250 1458h41l-250 -1458h-41zM481 178v37l172 514h99v-514h98v-37h-98v-141h79v-37h-256v37h78v141h-172zM518 215h135v397z" />
<glyph unicode="&#xbd;" horiz-adv-x="913" d="M61 1192q41 63 66 134t25 132h98v-692h80v-37h-256v37h78v524q-12 -29 -21 -45q-16 -33 -41 -65zM301 0l250 1458h41l-250 -1458h-41zM532 0v51q0 96 104.5 264t104.5 271q0 119 -65 119q-45 0 -76 -29t-31 -74q0 -35 19 -35q6 0 13 9.5t15 9.5q18 0 28.5 -14.5 t10.5 -30.5q0 -31 -18.5 -48.5t-42.5 -17.5q-33 0 -47.5 36t-14.5 69q0 68 43 114.5t107 46.5q72 0 121 -45t49 -110q0 -102 -138.5 -253t-138.5 -235h179q45 0 45 45v45h37v-188h-304z" />
<glyph unicode="&#x405;" horiz-adv-x="913" d="M61 1192q41 63 66 134t25 132h98v-692h80v-37h-256v37h78v524q-12 -29 -21 -45q-16 -33 -41 -65zM301 0l250 1458h41l-250 -1458h-41zM532 0v51q0 96 104.5 264t104.5 271q0 119 -65 119q-45 0 -76 -29t-31 -74q0 -35 19 -35q6 0 13 9.5t15 9.5q18 0 28.5 -14.5 t10.5 -30.5q0 -31 -18.5 -48.5t-42.5 -17.5q-33 0 -47.5 36t-14.5 69q0 68 43 114.5t107 46.5q72 0 121 -45t49 -110q0 -102 -138.5 -253t-138.5 -235h179q45 0 45 45v45h37v-188h-304z" />
<glyph unicode="&#xbe;" horiz-adv-x="913" d="M61 862q0 55 29 92t72 37q25 0 41 -16.5t16 -42.5q0 -25 -16.5 -41.5t-40.5 -16.5q-10 0 -22.5 9.5t-20.5 9.5q-20 0 -21 -31q0 -41 30 -68.5t71 -27.5q39 0 66.5 34t27.5 81v127q0 53 -4 67q-12 43 -76 43h-51v37h51q31 0 47 32t16 64v119q0 33 -17 54.5t-44 21.5 q-39 0 -67.5 -26.5t-28.5 -65.5q0 -18 18 -19q8 0 17 4q20 10 24 11q41 0 41 -43q0 -23 -15.5 -42.5t-45.5 -19.5q-31 0 -53.5 32t-22.5 77q0 55 39 92t98 37q66 0 113 -51.5t47 -126.5q0 -55 -31 -104.5t-86 -61.5q72 -12 107 -72q29 -47 28 -113q0 -92 -59 -158.5 t-143 -66.5q-55 0 -94.5 39t-39.5 94zM313 0l250 1458h41l-250 -1458h-41zM479 178v37l172 514h99v-514h98v-37h-98v-141h79v-37h-256v37h78v141h-172zM516 215h135v397z" />
<glyph unicode="&#x455;" horiz-adv-x="913" d="M61 862q0 55 29 92t72 37q25 0 41 -16.5t16 -42.5q0 -25 -16.5 -41.5t-40.5 -16.5q-10 0 -22.5 9.5t-20.5 9.5q-20 0 -21 -31q0 -41 30 -68.5t71 -27.5q39 0 66.5 34t27.5 81v127q0 53 -4 67q-12 43 -76 43h-51v37h51q31 0 47 32t16 64v119q0 33 -17 54.5t-44 21.5 q-39 0 -67.5 -26.5t-28.5 -65.5q0 -18 18 -19q8 0 17 4q20 10 24 11q41 0 41 -43q0 -23 -15.5 -42.5t-45.5 -19.5q-31 0 -53.5 32t-22.5 77q0 55 39 92t98 37q66 0 113 -51.5t47 -126.5q0 -55 -31 -104.5t-86 -61.5q72 -12 107 -72q29 -47 28 -113q0 -92 -59 -158.5 t-143 -66.5q-55 0 -94.5 39t-39.5 94zM313 0l250 1458h41l-250 -1458h-41zM479 178v37l172 514h99v-514h98v-37h-98v-141h79v-37h-256v37h78v141h-172zM516 215h135v397z" />
<glyph unicode="&#xbf;" horiz-adv-x="462" d="M20 -266q0 162 43 294t87.5 273t44.5 320h49v-101q0 -29 -58 -416q-27 -180 -26 -370q0 -106 13 -189.5t560E8CF16AA9" />
<glyph unicode="&#x457;" horiz-adv-x="462" d="M20 -266q0 162 43 294t87.5 273t44.5 320h49v-101q0 -29 -58 -416q-27 -180 -26 -370q0 -106 13 -189.5t560E8CF16AA9" />
<glyph unicode="&#xc0;" horiz-adv-x="591" d="M10 0v37h62l200 1446h50l192 -1446h68v-37h-256v37h61l-70 471h-127l-65 -471h61v-37h-176zM193 545h120l-55 454z" />
<glyph unicode="&#x410;" horiz-adv-x="591" d="M10 0v37h62l200 1446h50l192 -1446h68v-37h-256v37h61l-70 471h-127l-65 -471h61v-37h-176zM193 545h120l-55 454z" />
<glyph unicode="&#xc1;" horiz-adv-x="559" d="M20 1421v37h443v-430h-37q0 166 -14 248q-27 145 -97 145h-73v-602h49q96 0 163.5 -125t67.5 -303q0 -164 -70.5 -277.5t-172.5 -113.5h-244v37h84v1384h-99zM242 37h37q51 0 85.5 73.5t34.5 180.5v237q0 104 -35.5 179t-84.5 75h-37v-745z" />
<glyph unicode="&#x411;" horiz-adv-x="559" d="M20 1421v37h443v-430h-37q0 166 -14 248q-27 145 -97 145h-73v-602h49q96 0 163.5 -125t67.5 -303q0 -164 -70.5 -277.5t-172.5 -113.5h-244v37h84v1384h-99zM242 37h37q51 0 85.5 73.5t34.5 180.5v237q0 104 -35.5 179t-84.5 75h-37v-745z" />
<glyph unicode="&#xc2;" horiz-adv-x="571" d="M20 0v37h99v1384h-84v37h219q147 0 207 -110q45 -84 45 -244q0 -123 -31 -211q-39 -113 -119 -131q78 -12 128.5 -124t50.5 -247q0 -164 -39 -254q-59 -137 -213 -137h-263zM242 37h47q66 0 96 123q23 90 23 229q0 141 -25 227q-37 129 -121 129h-20v-708zM242 782h18 q68 0 102 125q25 90 25 201q0 113 -25 197q-35 117 -106 116h-14v-639z" />
<glyph unicode="&#x412;" horiz-adv-x="571" d="M20 0v37h99v1384h-84v37h219q147 0 207 -110q45 -84 45 -244q0 -123 -31 -211q-39 -113 -119 -131q78 -12 128.5 -124t50.5 -247q0 -164 -39 -254q-59 -137 -213 -137h-263zM242 37h47q66 0 96 123q23 90 23 229q0 141 -25 227q-37 129 -121 129h-20v-708zM242 782h18 q68 0 102 125q25 90 25 201q0 113 -25 197q-35 117 -106 116h-14v-639z" />
<glyph unicode="&#xc3;" horiz-adv-x="483" d="M20 0v37h99v1384h-84v37h428v-430h-37q0 166 -14 248q-27 145 -97 145h-73v-1384h98v-37h-320z" />
<glyph unicode="&#x413;" horiz-adv-x="483" d="M20 0v37h99v1384h-84v37h428v-430h-37q0 166 -14 248q-27 145 -97 145h-73v-1384h98v-37h-320z" />
<glyph unicode="&#xc4;" horiz-adv-x="628" d="M10 37h62q61 84 93 180t32 234v970h-84v37h495v-37h-98v-1384h98v-336h-37q0 160 -14 213q-23 86 -96 86h-0199CA2A0D" />
<glyph unicode="&#x414;" horiz-adv-x="628" d="M10 37h62q61 84 93 180t32 234v970h-84v37h495v-37h-98v-1384h98v-336h-37q0 160 -14 213q-23 86 -96 86h-0199CA2A0D" />
<glyph unicode="&#xc5;" horiz-adv-x="524" d="M20 0v37h99v1384h-84v37h428v-430h-37q0 166 -14 248q-27 145 -97 145h-73v-659h41q49 0 65.5 67.5t16.5 194.5h36v-561h-36q0 135 -13 186q-18 76 -69 76h-41v-688h63q141 0 141 461h37v-498h-463z" />
<glyph unicode="&#x415;" horiz-adv-x="524" d="M20 0v37h99v1384h-84v37h428v-430h-37q0 166 -14 248q-27 145 -97 145h-73v-659h41q49 0 65.5 67.5t16.5 194.5h36v-561h-36q0 135 -13 186q-18 76 -69 76h-41v-688h63q141 0 141 461h37v-498h-463z" />
<glyph unicode="&#xc6;" horiz-adv-x="888" d="M0 0v37h61l242 823l-178 561h-62v37h175v-37h-62l207 -647v647h-98v37h319v-37h-98v-647l207 647h-62v37h174v-37h-61l-178 -561l241 -823h62v-37h-178l-185 672l-20 -66v-569h98v-37h-319v37h98v569l-21 66l-184 -672h-178z" />
<glyph unicode="&#x416;" horiz-adv-x="888" d="M0 0v37h61l242 823l-178 561h-62v37h175v-37h-62l207 -647v647h-98v37h319v-37h-98v-647l207 647h-62v37h174v-37h-61l-178 -561l241 -823h62v-37h-178l-185 672l-20 -66v-569h98v-37h-319v37h98v569l-21 66l-184 -672h-178z" />
<glyph unicode="&#xc7;" horiz-adv-x="509" d="M41 676h37q0 -319 37 -491.5t108 -172.5q53 0 86 56.5t33 117.5v349q0 137 -14 184q-20 68 -86 67h-64v37h092A98BAB4" />
<glyph unicode="&#x417;" horiz-adv-x="509" d="M41 676h37q0 -319 37 -491.5t108 -172.5q53 0 86 56.5t33 117.5v349q0 137 -14 184q-20 68 -86 67h-64v37h092A98BAB4" />
<glyph unicode="&#xc8;" horiz-adv-x="638" d="M20 0v37h99v1384h-84v37h268v-37h-61v-1026l155 920v106h-61v37h282v-37h-98v-1384h98v-37h-282v37h61v1053l-155 -922v-131h61v-37h-283z" />
<glyph unicode="&#x418;" horiz-adv-x="638" d="M20 0v37h99v1384h-84v37h268v-37h-61v-1026l155 920v106h-61v37h282v-37h-98v-1384h98v-37h-282v37h61v1053l-155 -922v-131h61v-37h-283z" />
<glyph unicode="&#xc9;" horiz-adv-x="638" d="M20 0v37h99v1384h-84v37h268v-37h-61v-1026l155 920v106h-61v37h282v-37h-98v-1384h98v-37h-282v37h61v10503B9BA0A5E" />
<glyph unicode="&#x419;" horiz-adv-x="638" d="M20 0v37h99v1384h-84v37h268v-37h-61v-1026l155 920v106h-61v37h282v-37h-98v-1384h98v-37h-282v37h61v10503B9BA0A5E" />
<glyph unicode="&#xca;" horiz-adv-x="624" d="M20 0v37h99v1384h-99v37h320v-37h-98v-647l207 647h-62v37h174v-37h-61l-178 -561l241 -823h62v-37h-179l-184 672l-20 -66v-569h98v-37h-320z" />
<glyph unicode="&#x41a;" horiz-adv-x="624" d="M20 0v37h99v1384h-99v37h320v-37h-98v-647l207 647h-62v37h174v-37h-61l-178 -561l241 -823h62v-37h-179l-184 672l-20 -66v-569h98v-37h-320z" />
<glyph unicode="&#xcb;" horiz-adv-x="694" d="M0 135q0 51 31.5 85t77.5 34q27 0 46 -19.5t19 -48.5t-17.5 -50t-41.5 -21q-8 0 -24.5 6t-22.5 6q-18 0 -1057F0EFA6D" />
<glyph unicode="&#x41b;" horiz-adv-x="694" d="M0 135q0 51 31.5 85t77.5 34q27 0 46 -19.5t19 -48.5t-17.5 -50t-41.5 -21q-8 0 -24.5 6t-22.5 6q-18 0 -1057F0EFA6D" />
<glyph unicode="&#xcc;" horiz-adv-x="847" d="M20 0v37h99v1384h-84v37h207l186 -1028l178 1028h221v-37h-98v-1384h98v-37h-319v37h98v1175l-198 -1185h-25l-219 1185l-4 -1175h98v-37h-238z" />
<glyph unicode="&#x41c;" horiz-adv-x="847" d="M20 0v37h99v1384h-84v37h207l186 -1028l178 1028h221v-37h-98v-1384h98v-37h-319v37h98v1175l-198 -1185h-25l-219 1185l-4 -1175h98v-37h-238z" />
<glyph unicode="&#xcd;" horiz-adv-x="638" d="M20 0v37h99v1384h-84v37h268v-37h-61v-659h155v659h-61v37h282v-37h-98v-1384h98v-37h-282v37h61v688h-155v-688h61v-37h-283z" />
<glyph unicode="&#x41d;" horiz-adv-x="638" d="M20 0v37h99v1384h-84v37h268v-37h-61v-659h155v659h-61v37h282v-37h-98v-1384h98v-37h-282v37h61v688h-155v-688h61v-37h-283z" />
<glyph unicode="&#xce;" horiz-adv-x="532" d="M41 631v180q0 293 56.5 482.5t168.5 189.5q111 0 168.5 -190.5t57.5 -481.5v-180q0 -313 -41 -463q-53 -193 -185 -193q-129 0 -182 191q-43 154 -43 465zM164 352q0 -135 16 -215q25 -125 86 -125t86 125q16 82 17 215v754q0 162 -11 219q-23 121 -92 121 q-68 0 -90 -121q-12 -68 -12 -219v-754z" />
<glyph unicode="&#x41e;" horiz-adv-x="532" d="M41 631v180q0 293 56.5 482.5t168.5 189.5q111 0 168.5 -190.5t57.5 -481.5v-180q0 -313 -41 -463q-53 -193 -185 -193q-129 0 -182 191q-43 154 -43 465zM164 352q0 -135 16 -215q25 -125 86 -125t86 125q16 82 17 215v754q0 162 -11 219q-23 121 -92 121 q-68 0 -90 -121q-12 -68 -12 -219v-754z" />
<glyph unicode="&#xcf;" horiz-adv-x="638" d="M20 0v37h99v1384h-84v37h583v-37h-98v-1384h98v-37h-282v37h61v1384h-155v-1384h61v-37h-283z" />
<glyph unicode="&#x41f;" horiz-adv-x="638" d="M20 0v37h99v1384h-84v37h583v-37h-98v-1384h98v-37h-282v37h61v1384h-155v-1384h61v-37h-283z" />
<glyph unicode="&#xd0;" horiz-adv-x="559" d="M20 0v37h99v1384h-84v37h244q117 0 180 -112.5t63 -278.5q0 -162 -67.5 -276.5t-163.5 -114.5h-49v37h37q47 0 83.5 70.5t36.5 166.5v217q0 109 -28.5 181.5t-91.5 72.5h-37v-1384h98v-37h-320z" />
<glyph unicode="&#x420;" horiz-adv-x="559" d="M20 0v37h99v1384h-84v37h244q117 0 180 -112.5t63 -278.5q0 -162 -67.5 -276.5t-163.5 -114.5h-49v37h37q47 0 83.5 70.5t36.5 166.5v217q0 109 -28.5 181.5t-91.5 72.5h-37v-1384h98v-37h-320z" />
<glyph unicode="&#xd1;" horiz-adv-x="485" d="M37 629v207q0 303 45 458q55 188 180 189q33 0 58.5 -17.5t54.5 -35.5q25 0 33 28h36v-551h-36q0 190 -31 344q-39 195 -111 195q-80 0 -98 -156q-8 -72 -8 -160v-794q0 -129 16 -207q25 -117 86 -117q70 0 108 188.5t38 512.5h36q0 -362 -38 -537q-45 -201 -144 -201 q-129 0 -182 191q-43 154 -43 463z" />
<glyph unicode="&#x421;" horiz-adv-x="485" d="M37 629v207q0 303 45 458q55 188 180 189q33 0 58.5 -17.5t54.5 -35.5q25 0 33 28h36v-551h-36q0 190 -31 344q-39 195 -111 195q-80 0 -98 -156q-8 -72 -8 -160v-794q0 -129 16 -207q25 -117 86 -117q70 0 108 188.5t38 512.5h36q0 -362 -38 -537q-45 -201 -144 -201 q-129 0 -182 191q-43 154 -43 463z" />
<glyph unicode="&#xd2;" horiz-adv-x="516" d="M20 979v479h476v-479h-37q0 193 -15 283q-27 160 -96 159h-29v-1384h99v-37h-320v37h99v1384h-29q-82 0 -102 -227q-8 -94 -9 -215h-37z" />
<glyph unicode="&#x422;" horiz-adv-x="516" d="M20 979v479h476v-479h-37q0 193 -15 283q-27 160 -96 159h-29v-1384h99v-37h-320v37h99v1384h-29q-82 0 -102 -227q-8 -94 -9 -215h-37z" />
<glyph unicode="&#xd3;" horiz-adv-x="528" d="M20 1421v37h242v-37h-61l112 -782l103 782h-84v37h196v-37h-61l-170 -1196v-110q0 -59 -38 -99.5t-93 -40.5q-63 0 -98 39t-35 109q0 51 31.5 85t76.5 34q27 0 46.5 -19.5t19.5 -48.5t-17.5 -50.5t-42.5 -21.5q-8 0 -24.5 6.5t-22.5 6.5q-18 0 -18 -37q0 -29 28.5 -47.5 t61.5 -18.5q35 0 59.5 29t24.5 74v110l-174 1196h-62z" />
<glyph unicode="&#x423;" horiz-adv-x="528" d="M20 1421v37h242v-37h-61l112 -782l103 782h-84v37h196v-37h-61l-170 -1196v-110q0 -59 -38 -99.5t-93 -40.5q-63 0 -98 39t-35 109q0 51 31.5 85t76.5 34q27 0 46.5 -19.5t19.5 -48.5t-17.5 -50.5t-42.5 -21.5q-8 0 -24.5 6.5t-22.5 6.5q-18 0 -18 -37q0 -29 28.5 -47.5 t61.5 -18.5q35 0 59.5 29t24.5 74v110l-174 1196h-62z" />
<glyph unicode="&#xd4;" horiz-adv-x="745" d="M20 758q0 264 63.5 405.5t190.5 141.5h37v116h-98v37h319v-37h-98v-116h37q125 0 189.5 -144.5t64.5 -402.5q0 -256 -65.5 -406.5t-198.5 -150.5h-27v-164h98v-37h-319v37h98v164h-26q-133 0 -199 150.5t-66 406.5zM143 598q0 -147 40 -253.5t91 -106.5h37v1030h-37 q-68 0 -104 -135q-27 -100 -27 -234v-301zM434 238h37q51 0 91 105.5t40 254.5v301q0 131 -27 234q-35 135 -104 135h-37v-1030z" />
<glyph unicode="&#x424;" horiz-adv-x="745" d="M20 758q0 264 63.5 405.5t190.5 141.5h37v116h-98v37h319v-37h-98v-116h37q125 0 189.5 -144.5t64.5 -402.5q0 -256 -65.5 -406.5t-198.5 -150.5h-27v-164h98v-37h-319v37h98v164h-26q-133 0 -199 150.5t-66 406.5zM143 598q0 -147 40 -253.5t91 -106.5h37v1030h-37 q-68 0 -104 -135q-27 -100 -27 -234v-301zM434 238h37q51 0 91 105.5t40 254.5v301q0 131 -27 234q-35 135 -104 135h-37v-1030z" />
<glyph unicode="&#xd5;" horiz-adv-x="573" d="M10 1421v37h242v-37h-62l99 -483l90 483h-62v37h183v-37h-80l-103 -596l160 -788h86v-37h-270v37h61l-110 512l-97 -512h62v-37h-182v37h79l109 653l-143 731h-62z" />
<glyph unicode="&#x425;" horiz-adv-x="573" d="M10 1421v37h242v-37h-62l99 -483l90 483h-62v37h183v-37h-80l-103 -596l160 -788h86v-37h-270v37h61l-110 512l-97 -512h62v-37h-182v37h79l109 653l-143 731h-62z" />
<glyph unicode="&#xd6;" horiz-adv-x="638" d="M20 0v37h99v1384h-84v37h268v-37h-61v-1384h155v1384h-61v37h282v-37h-98v-1384h98v-336h-36q0 160 -15 213q-23 86 -96 86h-451z" />
<glyph unicode="&#x426;" horiz-adv-x="638" d="M20 0v37h99v1384h-84v37h268v-37h-61v-1384h155v1384h-61v37h282v-37h-98v-1384h98v-336h-36q0 160 -15 213q-23 86 -96 86h-451z" />
<glyph unicode="&#xd7;" horiz-adv-x="614" d="M10 1421v37h269v-37h-62v-514q0 -80 21.5 -132t58.5 -52h76v698h-62v37h283v-37h-98v-1384h98v-37h-283v37h62v649h-82q-86 0 -141.5 74t-55.5 203v458h-84z" />
<glyph unicode="&#x427;" horiz-adv-x="614" d="M10 1421v37h269v-37h-62v-514q0 -80 21.5 -132t58.5 -52h76v698h-62v37h283v-37h-98v-1384h98v-37h-283v37h62v649h-82q-86 0 -141.5 74t-55.5 203v458h-84z" />
<glyph unicode="&#xd8;" horiz-adv-x="917" d="M20 0v37h99v1384h-84v37h268v-37h-61v-1384h155v1384h-61v37h246v-37h-62v-1384h156v1384h-62v37h283v-37h-98v-1384h98v-37h-877z" />
<glyph unicode="&#x428;" horiz-adv-x="917" d="M20 0v37h99v1384h-84v37h268v-37h-61v-1384h155v1384h-61v37h246v-37h-62v-1384h156v1384h-62v37h283v-37h-98v-1384h98v-37h-877z" />
<glyph unicode="&#xd9;" horiz-adv-x="917" d="M20 0v37h99v1384h-84v37h268v-37h-61v-1384h155v1384h-61v37h246v-37h-62v-1384h156v1384h-62v37h283v-37h-98v-1384h98v-336h-37q0 160 -14 213q-23 86 -96 86h-730z" />
<glyph unicode="&#x429;" horiz-adv-x="917" d="M20 0v37h99v1384h-84v37h268v-37h-61v-1384h155v1384h-61v37h246v-37h-62v-1384h156v1384h-62v37h283v-37h-98v-1384h98v-336h-37q0 160 -14 213q-23 86 -96 86h-730z" />
<glyph unicode="&#xda;" horiz-adv-x="610" d="M20 979v479h398v-37h-99v-602h50q96 0 163.5 -125t67.5 -303q0 -164 -70.5 -277.5t-173.5 -113.5h-243v37h84v1384h-29q-82 0 -102 -227q-8 -94 -9 -215h-37zM319 37h37q51 0 86 73.5t35 180.5v237q0 104 -35.5 179t-85.5 75h-37v-745z" />
<glyph unicode="&#x42a;" horiz-adv-x="610" d="M20 979v479h398v-37h-99v-602h50q96 0 163.5 -125t67.5 -303q0 -164 -70.5 -277.5t-173.5 -113.5h-243v37h84v1384h-29q-82 0 -102 -227q-8 -94 -9 -215h-37zM319 37h37q51 0 86 73.5t35 180.5v237q0 104 -35.5 179t-85.5 75h-37v-745z" />
<glyph unicode="&#xdb;" horiz-adv-x="835" d="M20 1421v37h320v-37h-98v-602h49q96 0 163.5 -125t67.5 -303q0 -164 -70.5 -277.5t-172.5 -113.5h-244v37h84v1384h-99zM242 37h37q51 0 85.5 73.5t34.5 180.5v237q0 104 -35.5 179t-84.5 75h-37v-745zM496 0v37h98v1384h-98v37h319v-37h-98v-1384h98v-37h-319z" />
<glyph unicode="&#x42b;" horiz-adv-x="835" d="M20 1421v37h320v-37h-98v-602h49q96 0 163.5 -125t67.5 -303q0 -164 -70.5 -277.5t-172.5 -113.5h-244v37h84v1384h-99zM242 37h37q51 0 85.5 73.5t34.5 180.5v237q0 104 -35.5 179t-84.5 75h-37v-745zM496 0v37h98v1384h-98v37h319v-37h-98v-1384h98v-37h-319z" />
<glyph unicode="&#xdc;" horiz-adv-x="532" d="M20 1421v37h320v-37h-98v-602h49q96 0 163.5 -125t67.5 -303q0 -164 -70.5 -277.5t-172.5 -113.5h-244v37h84v1384h-99zM242 37h37q51 0 85.5 73.5t34.5 180.5v237q0 104 -35.5 179t-84.5 75h-37v-745z" />
<glyph unicode="&#x42c;" horiz-adv-x="532" d="M20 1421v37h320v-37h-98v-602h49q96 0 163.5 -125t67.5 -303q0 -164 -70.5 -277.5t-172.5 -113.5h-244v37h84v1384h-99zM242 37h37q51 0 85.5 73.5t34.5 180.5v237q0 104 -35.5 179t-84.5 75h-37v-745z" />
<glyph unicode="&#xdd;" horiz-adv-x="485" d="M41 713h37q0 -324 38 -512.5t107 -188.5q61 0 86 117q16 78 17 207v389h-41q-49 0 -65.5 -67.5t-16.5 -194.5h-37v561h37q0 -135 15 -198.5t67 -63.5h41v368q0 150 -13 207q-23 109 -94 109q-72 0 -110 -195q-31 -152 -31 -344h-37v576h37q6 -23 13 -38t20 -15 q12 0 40.5 26.5t71.5 26.5q123 0 178 -187q47 -160 48 -460v-207q0 -315 -41 -463q-53 -190 -185 -191q-96 0 -139 193t-43 545z" />
<glyph unicode="&#x42d;" horiz-adv-x="485" d="M41 713h37q0 -324 38 -512.5t107 -188.5q61 0 86 117q16 78 17 207v389h-41q-49 0 -65.5 -67.5t-16.5 -194.5h-37v561h37q0 -135 15 -198.5t67 -63.5h41v368q0 150 -13 207q-23 109 -94 109q-72 0 -110 -195q-31 -152 -31 -344h-37v576h37q6 -23 13 -38t20 -15 q12 0 40.5 26.5t71.5 26.5q123 0 178 -187q47 -160 48 -460v-207q0 -315 -41 -463q-53 -190 -185 -191q-96 0 -139 193t-43 545z" />
<glyph unicode="&#xde;" horiz-adv-x="827" d="M20 0v37h99v1384h-99v37h320v-37h-98v-659h98v49q0 293 56.5 482.5t168.5 189.5q111 0 168.5 -190.5t57.5 -481.5v-180q0 -313 -41 -463q-53 -193 -185 -193q-129 0 -182 191q-43 154 -43 465v94h-98v-688h98v-37h-320zM463 352q0 -135 16 -215q25 -125 86 -125t86 125 q16 82 17 215v754q0 162 -11 219q-23 121 -92 121q-68 0 -90 -121q-12 -68 -12 -219v-754z" />
<glyph unicode="&#x42e;" horiz-adv-x="827" d="M20 0v37h99v1384h-99v37h320v-37h-98v-659h98v49q0 293 56.5 482.5t168.5 189.5q111 0 168.5 -190.5t57.5 -481.5v-180q0 -313 -41 -463q-53 -193 -185 -193q-129 0 -182 191q-43 154 -43 465v94h-98v-688h98v-37h-320zM463 352q0 -135 16 -215q25 -125 86 -125t86 125 q16 82 17 215v754q0 162 -11 219q-23 121 -92 121q-68 0 -90 -121q-12 -68 -12 -219v-754z" />
<glyph unicode="&#xdf;" horiz-adv-x="628" d="M0 0v37h61l170 708q-66 45 -98 119q-39 86 -39 223q0 371 254 371h246v-37h-84v-1384h98v-37h-319v37h98v672h-53l-164 -709h-170zM215 983q0 -109 38 -173.5t97 -64.5h37v676h-39q-70 0 -101.5 -66.5t-31.5 -180.5v-191z" />
<glyph unicode="&#x42f;" horiz-adv-x="628" d="M0 0v37h61l170 708q-66 45 -98 119q-39 86 -39 223q0 371 254 371h246v-37h-84v-1384h98v-37h-319v37h98v672h-53l-164 -709h-170zM215 983q0 -109 38 -173.5t97 -64.5h37v676h-39q-70 0 -101.5 -66.5t-31.5 -180.5v-191z" />
<glyph unicode="&#xe0;" d="M37 233q0 133 31 209q41 102 143 103q12 0 29.5 -7.5t29.5 -19.5v293q0 27 -13 49.5t-40 22.5q-31 0 -67.50C8188AA08" />
<glyph unicode="&#x430;" d="M37 233q0 133 31 209q41 102 143 103q12 0 29.5 -7.5t29.5 -19.5v293q0 27 -13 49.5t-40 22.5q-31 0 -67.50C8188AA08" />
<glyph unicode="&#xe1;" horiz-adv-x="444" d="M41 471v799q0 104 30.5 158.5t80.5 54.5q37 0 65 -6q84 -18 102 -19q49 0 50 25h37q0 -55 -28 -91t-69 -36q-33 0 -65.5 12t-65.5 12q-37 0 -66.5 -45t-29.5 -106v-484q12 96 49 135.5t96 39.5q111 0 152 -158q27 -100 27 -293q0 -225 -19 -311q-37 -170 -160 -170 q-102 0 -149 168q-37 131 -37 315zM160 182q0 -72 8 -100q16 -57 59 -57q49 0 62 81q6 39 6 78v496q0 84 -10 129q-16 74 -58 74q-45 0 -56 -55.5t-11 -147.5v-498z" />
<glyph unicode="&#x431;" horiz-adv-x="444" d="M41 471v799q0 104 30.5 158.5t80.5 54.5q37 0 65 -6q84 -18 102 -19q49 0 50 25h37q0 -55 -28 -91t-69 -36q-33 0 -65.5 12t-65.5 12q-37 0 -66.5 -45t-29.5 -106v-484q12 96 49 135.5t96 39.5q111 0 152 -158q27 -100 27 -293q0 -225 -19 -311q-37 -170 -160 -170 q-102 0 -149 168q-37 131 -37 315zM160 182q0 -72 8 -100q16 -57 59 -57q49 0 62 81q6 39 6 78v496q0 84 -10 129q-16 74 -58 74q-45 0 -56 -55.5t-11 -147.5v-498z" />
<glyph unicode="&#xe2;" horiz-adv-x="505" d="M20 0v37h72v833h-72v37h197q133 0 191 -67q45 -53 45 -152q0 -72 -33 -131q-39 -70 -111 -82q72 -8 119 -77.5t47 -153.5q0 -98 -39 -158q-57 -86 -192 -86h-224zM207 37h41q61 0 88 67q20 51 20 140q0 90 -22 141q-31 72 -109 72h-18v-420zM207 494h16q47 0 76 43 q39 59 39 155q0 72 -23 117q-31 61 -96 61h-12v-376z" />
<glyph unicode="&#x432;" horiz-adv-x="505" d="M20 0v37h72v833h-72v37h197q133 0 191 -67q45 -53 45 -152q0 -72 -33 -131q-39 -70 -111 -82q72 -8 119 -77.5t47 -153.5q0 -98 -39 -158q-57 -86 -192 -86h-224zM207 37h41q61 0 88 67q20 51 20 140q0 90 -22 141q-31 72 -109 72h-18v-420zM207 494h16q47 0 76 43 q39 59 39 155q0 72 -23 117q-31 61 -96 61h-12v-376z" />
<glyph unicode="&#xe3;" horiz-adv-x="417" d="M20 0v37h72v833h-72v37h377v-336h-37q0 160 -14 213q-23 86 -96 86h-43v-833h72v-37h-259z" />
<glyph unicode="&#x433;" horiz-adv-x="417" d="M20 0v37h72v833h-72v37h377v-336h-37q0 160 -14 213q-23 86 -96 86h-43v-833h72v-37h-259z" />
<glyph unicode="&#xe4;" horiz-adv-x="479" d="M4 -428q0 51 32 85t77 34q27 0 46 -19.5t19 -48.5t-17.5 -50.5t-41.5 -21.5q-8 0 -24.5 6.5t-22.5 6.5q-18 0 -19 -37q0 -29 29 -47.5t61 -18.5q92 0 123 123q16 66 17 209v254q-14 -25 -35 -42t-53 -17q-78 0 -118 118.5t-40 354.5q0 184 24 284q43 174 158 175 q41 0 60 -41l4 28h176v-37h-62v-1077q0 -156 -72.5 -262t-187.5 -106q-63 0 -98 38.5t-35 108.5zM156 465q0 -217 12 -322.5t57 -105.5q39 0 51 84q6 43 7 162v346q0 123 -13.5 182t-44.5 59q-45 0 -57 -100t-12 -305z" />
<glyph unicode="&#x434;" horiz-adv-x="479" d="M4 -428q0 51 32 85t77 34q27 0 46 -19.5t19 -48.5t-17.5 -50.5t-41.5 -21.5q-8 0 -24.5 6.5t-22.5 6.5q-18 0 -19 -37q0 -29 29 -47.5t61 -18.5q92 0 123 123q16 66 17 209v254q-14 -25 -35 -42t-53 -17q-78 0 -118 118.5t-40 354.5q0 184 24 284q43 174 158 175 q41 0 60 -41l4 28h176v-37h-62v-1077q0 -156 -72.5 -262t-187.5 -106q-63 0 -98 38.5t-35 108.5zM156 465q0 -217 12 -322.5t57 -105.5q39 0 51 84q6 43 7 162v346q0 123 -13.5 182t-44.5 59q-45 0 -57 -100t-12 -305z" />
<glyph unicode="&#xe5;" horiz-adv-x="421" d="M37 438q0 213 29 320q43 162 159 162q72 0 113 -93q53 -119 53 -335h-235v-314q0 -78 18.5 -109.5t48.5 -304077D1ACC" />
<glyph unicode="&#x435;" horiz-adv-x="421" d="M37 438q0 213 29 320q43 162 159 162q72 0 113 -93q53 -119 53 -335h-235v-314q0 -78 18.5 -109.5t48.5 -304077D1ACC" />
<glyph unicode="&#xe6;" horiz-adv-x="794" d="M0 0v37h61l185 559l-140 274h-79v37h182v-37h-62l193 -387v938h-84v37h199v-975l192 387h-61v37h182v-37h-80l-139 -274l184 -559h62v-37h-166l-144 465l-30 -57v-371h61v-37h-237v37h61v371l-31 57l-143 -465h-166z" />
<glyph unicode="&#x436;" horiz-adv-x="794" d="M0 0v37h61l185 559l-140 274h-79v37h182v-37h-62l193 -387v938h-84v37h199v-975l192 387h-61v37h182v-37h-80l-139 -274l184 -559h62v-37h-166l-144 465l-30 -57v-371h61v-37h-237v37h61v371l-31 57l-143 -465h-166z" />
<glyph unicode="&#xe7;" horiz-adv-x="458" d="M37 369h37q0 -147 38 -245.5t95 -98.5q45 0 70.5 61t25.5 158q0 90 -22 141q-31 72 -109 72h-39v37h37q61 0 90 69q20 51 21 129q0 82 -13 123q-20 68 -69 68q-45 0 -77 -92.5t-32 -219.5h-37v349h37q0 -10 7 -23.5t14 -13.5q29 14 53 25.5t51 11.5q90 0 135 -67t45 -165 q0 -74 -30 -131q-37 -70 -109 -82q72 -8 119 -77.5t47 -153.5q0 -115 -55.5 -192t-151.5 -77q-88 0 -133 110t-45 284z" />
<glyph unicode="&#x437;" horiz-adv-x="458" d="M37 369h37q0 -147 38 -245.5t95 -98.5q45 0 70.5 61t25.5 158q0 90 -22 141q-31 72 -109 72h-39v37h37q61 0 90 69q20 51 21 129q0 82 -13 123q-20 68 -69 68q-45 0 -77 -92.5t-32 -219.5h-37v349h37q0 -10 7 -23.5t14 -13.5q29 14 53 25.5t51 11.5q90 0 135 -67t45 -165 q0 -74 -30 -131q-37 -70 -109 -82q72 -8 119 -77.5t47 -153.5q0 -115 -55.5 -192t-151.5 -77q-88 0 -133 110t-45 284z" />
<glyph unicode="&#xe8;" horiz-adv-x="542" d="M20 0v37h72v833h-72v37h236v-37h-49v-616l129 594v22h-49v37h235v-37h-71v-833h71v-37h-235v37h49v633l-129 -590v-43h49v-37h-236z" />
<glyph unicode="&#x438;" horiz-adv-x="542" d="M20 0v37h72v833h-72v37h236v-37h-49v-616l129 594v22h-49v37h235v-37h-71v-833h71v-37h-235v37h49v633l-129 -590v-43h49v-37h-236z" />
<glyph unicode="&#xe9;" horiz-adv-x="542" d="M20 0v37h72v833h-72v37h236v-37h-49v-616l129 594v22h-49v37h235v-37h-71v-833h71v-37h-235v37h49v633l-129 -590v-43h49v-37h-236zM92 1159q0 45 22.5 76t55.5 31q29 0 47.5 -18.5t18.5 -49.5q0 -72 -50 -72q-37 0 -36 -20q0 -20 35.5 -41t84.5 -21q47 0 86 21.5 t39 42.5q0 18 -39 18q-25 0 -37 20.5t-12 51.5q0 27 18.5 47.5t49.5 20.5t53.5 -31t22.5 -76q0 -61 -52.5 -106t-128.5 -45q-78 0 -128 44t-50 107z" />
<glyph unicode="&#x439;" horiz-adv-x="542" d="M20 0v37h72v833h-72v37h236v-37h-49v-616l129 594v22h-49v37h235v-37h-71v-833h71v-37h-235v37h49v633l-129 -590v-43h49v-37h-236zM92 1159q0 45 22.5 76t55.5 31q29 0 47.5 -18.5t18.5 -49.5q0 -72 -50 -72q-37 0 -36 -20q0 -20 35.5 -41t84.5 -21q47 0 86 21.5 t39 42.5q0 18 -39 18q-25 0 -37 20.5t-12 51.5q0 27 18.5 47.5t49.5 20.5t53.5 -31t22.5 -76q0 -61 -52.5 -106t-128.5 -45q-78 0 -128 44t-50 107z" />
<glyph unicode="&#xea;" horiz-adv-x="548" d="M10 1421v37h199v-975l192 387h-61v37h182v-37h-80l-139 -274l184 -559h62v-37h-166l-143 465l-31 -57v-371h61v-37h-237v37h61v1384h-84z" />
<glyph unicode="&#x43a;" horiz-adv-x="548" d="M10 1421v37h199v-975l192 387h-61v37h182v-37h-80l-139 -274l184 -559h62v-37h-166l-143 465l-31 -57v-371h61v-37h-237v37h61v1384h-84z" />
<glyph unicode="&#xeb;" horiz-adv-x="591" d="M0 135q0 51 31.5 85t77.5 34q27 0 46 -19.5t19 -48.5t-17.5 -50t-41.5 -21q-8 0 -24.5 6t-22.5 6q-18 0 -10F2F89AA82" />
<glyph unicode="&#x43b;" horiz-adv-x="591" d="M0 135q0 51 31.5 85t77.5 34q27 0 46 -19.5t19 -48.5t-17.5 -50t-41.5 -21q-8 0 -24.5 6t-22.5 6q-18 0 -10F2F89AA82" />
<glyph unicode="&#xec;" horiz-adv-x="675" d="M10 0v37h72v833h-72v37h172l140 -620l147 620h186v-37h-71v-833h71v-37h-258v37h72v659l-162 -659h-24l-156 659l-4 -659h72v-37h-185z" />
<glyph unicode="&#x43c;" horiz-adv-x="675" d="M10 0v37h72v833h-72v37h172l140 -620l147 620h186v-37h-71v-833h71v-37h-258v37h72v659l-162 -659h-24l-156 659l-4 -659h72v-37h-185z" />
<glyph unicode="&#xed;" horiz-adv-x="542" d="M20 0v37h72v833h-72v37h236v-37h-49v-342h129v342h-49v37h235v-37h-71v-833h71v-37h-235v37h49v455h-129v-455h49v-37h-236z" />
<glyph unicode="&#x43d;" horiz-adv-x="542" d="M20 0v37h72v833h-72v37h236v-37h-49v-342h129v342h-49v37h235v-37h-71v-833h71v-37h-235v37h49v455h-129v-455h49v-37h-236z" />
<glyph unicode="&#xee;" horiz-adv-x="454" d="M41 471q0 182 37 299q47 150 149 150t150 -148q37 -117 37 -303q0 -193 -35 -313q-49 -168 -152 -168q-100 0 -149 168q-37 127 -37 315zM160 182q0 -72 8 -100q16 -57 59 -57q49 0 62 81q6 39 6 78v496q0 84 -10 129q-16 74 -58 74q-47 0 -61 -105q-6 -47 -6 -98v-498z " />
<glyph unicode="&#x43e;" horiz-adv-x="454" d="M41 471q0 182 37 299q47 150 149 150t150 -148q37 -117 37 -303q0 -193 -35 -313q-49 -168 -152 -168q-100 0 -149 168q-37 127 -37 315zM160 182q0 -72 8 -100q16 -57 59 -57q49 0 62 81q6 39 6 78v496q0 84 -10 129q-16 74 -58 74q-47 0 -61 -105q-6 -47 -6 -98v-498z " />
<glyph unicode="&#xef;" horiz-adv-x="542" d="M20 0v37h72v833h-72v37h502v-37h-71v-833h71v-37h-235v37h49v833h-129v-833h49v-37h-236z" />
<glyph unicode="&#x43f;" horiz-adv-x="542" d="M20 0v37h72v833h-72v37h502v-37h-71v-833h71v-37h-235v37h49v833h-129v-833h49v-37h-236z" />
<glyph unicode="&#xf0;" horiz-adv-x="497" d="M20 870v37h199v-51q18 33 40 48.5t50 15.5q90 0 125 -172q23 -109 23 -261q0 -252 -40 -375.5t-120 -123.5q-27 0 -43 16t-31 45l-4 -575h62v-37h-238v37h61v1396h-84zM219 195q0 -55 21.5 -106.5t42.5 -51.5q29 0 42 65.5t13 135.5v450q0 80 -14.5 131t-38.5 51 q-23 0 -44.5 -66.5t-21.5 -162.5v-446z" />
<glyph unicode="&#x440;" horiz-adv-x="497" d="M20 870v37h199v-51q18 33 40 48.5t50 15.5q90 0 125 -172q23 -109 23 -261q0 -252 -40 -375.5t-120 -123.5q-27 0 -43 16t-31 45l-4 -575h62v-37h-238v37h61v1396h-84zM219 195q0 -55 21.5 -106.5t42.5 -51.5q29 0 42 65.5t13 135.5v450q0 80 -14.5 131t-38.5 51 q-23 0 -44.5 -66.5t-21.5 -162.5v-446z" />
<glyph unicode="&#xf1;" horiz-adv-x="385" d="M41 434q0 170 39 307q51 178 141 179q16 0 39 -12.5t33 -12.5q18 0 18 25h37v-336h-37q0 121 -26.5 210t-59.5 89q-66 0 -65 -201v-530q0 -115 55 -115q45 0 70.5 119.5t25.5 296.5h37q0 -215 -29 -324q-37 -141 -126 -141q-80 0 -116 128t-36 318z" />
<glyph unicode="&#x441;" horiz-adv-x="385" d="M41 434q0 170 39 307q51 178 141 179q16 0 39 -12.5t33 -12.5q18 0 18 25h37v-336h-37q0 121 -26.5 210t-59.5 89q-66 0 -65 -201v-530q0 -115 55 -115q45 0 70.5 119.5t25.5 296.5h37q0 -215 -29 -324q-37 -141 -126 -141q-80 0 -116 128t-36 318z" />
<glyph unicode="&#xf2;" horiz-adv-x="503" d="M20 571v336h463v-336h-37q0 160 -14 213q-23 86 -96 86h-27v-833h72v-37h-258v37h72v833h-27q-72 0 -91.5 -73.5t-19.5 -225.5h-37z" />
<glyph unicode="&#x442;" horiz-adv-x="503" d="M20 571v336h463v-336h-37q0 160 -14 213q-23 86 -96 86h-27v-833h72v-37h-258v37h72v833h-27q-72 0 -91.5 -73.5t-19.5 -225.5h-37z" />
<glyph unicode="&#xf3;" horiz-adv-x="456" d="M-47 -496q0 27 18.5 45.5t44.5 18.5q31 0 45.5 -35t24.5 -35q14 0 31.5 34t25.5 95l56 373l-131 870h-62v3066CAC0A27" />
<glyph unicode="&#x443;" horiz-adv-x="456" d="M-47 -496q0 27 18.5 45.5t44.5 18.5q31 0 45.5 -35t24.5 -35q14 0 31.5 34t25.5 95l56 373l-131 870h-62v3066CAC0A27" />
<glyph unicode="&#xf4;" horiz-adv-x="679" d="M41 465q0 190 18 283q35 172 134 172q29 0 53 -18.5t33 -45.5l4 565h-84v37h198v-602q18 33 40 48.5t50 15.5q109 0 140 -246q12 -96 12 -209q0 -186 -23 -293q-39 -184 -141 -184q-20 0 -40.5 17.5t-33.5 43.5l-4 -575h62v-37h-238v37h62v575q-14 -27 -35 -44t-53 -17 q-98 0 -134 180q-20 107 -20 297zM160 465q0 -225 10 -326.5t55 -101.5q33 0 45.5 73.5t12.5 172.5v358q0 94 -14.5 161.5t-51.5 67.5q-43 0 -50 -99t-7 -224v-82zM397 285q0 -141 14.5 -194.5t43.5 -53.5q41 0 53 107.5t12 320.5q0 207 -10 306t-47 99t-51.5 -68.5 t-14.5 -160.5v-356z" />
<glyph unicode="&#x444;" horiz-adv-x="679" d="M41 465q0 190 18 283q35 172 134 172q29 0 53 -18.5t33 -45.5l4 565h-84v37h198v-602q18 33 40 48.5t50 15.5q109 0 140 -246q12 -96 12 -209q0 -186 -23 -293q-39 -184 -141 -184q-20 0 -40.5 17.5t-33.5 43.5l-4 -575h62v-37h-238v37h62v575q-14 -27 -35 -44t-53 -17 q-98 0 -134 180q-20 107 -20 297zM160 465q0 -225 10 -326.5t55 -101.5q33 0 45.5 73.5t12.5 172.5v358q0 94 -14.5 161.5t-51.5 67.5q-43 0 -50 -99t-7 -224v-82zM397 285q0 -141 14.5 -194.5t43.5 -53.5q41 0 53 107.5t12 320.5q0 207 -10 306t-47 99t-51.5 -68.5 t-14.5 -160.5v-356z" />
<glyph unicode="&#xf5;" horiz-adv-x="456" d="M20 0v37h62l115 385l-119 448h-58v37h216v-37h-43l63 -249l80 249h-45v37h147v-37h-61l-101 -344l123 -489h47v-37h-210v37h61l-78 313l-92 -313h45v-37h-152z" />
<glyph unicode="&#x445;" horiz-adv-x="456" d="M20 0v37h62l115 385l-119 448h-58v37h216v-37h-43l63 -249l80 249h-45v37h147v-37h-61l-101 -344l123 -489h47v-37h-210v37h61l-78 313l-92 -313h45v-37h-152z" />
<glyph unicode="&#xf6;" horiz-adv-x="542" d="M20 0v37h72v833h-72v37h236v-37h-49v-833h129v833h-49v37h235v-37h-71v-833h61v-336h-37q0 160 -14 213q-23 86 -96 86h-345z" />
<glyph unicode="&#x446;" horiz-adv-x="542" d="M20 0v37h72v833h-72v37h236v-37h-49v-833h129v833h-49v37h235v-37h-71v-833h61v-336h-37q0 160 -14 213q-23 86 -96 86h-345z" />
<glyph unicode="&#xf7;" d="M10 870v37h226v-37h-50v-342q0 -51 21.5 -81.5t46.5 -30.5h61v454h-49v37h226v-37h-62v-833h62v-37h-238v37h61v342h-94q-68 0 -108.5 41t-40.5 115v335h-62z" />
<glyph unicode="&#x447;" d="M10 870v37h226v-37h-50v-342q0 -51 21.5 -81.5t46.5 -30.5h61v454h-49v37h226v-37h-62v-833h62v-37h-238v37h61v342h-94q-68 0 -108.5 41t-40.5 115v335h-62z" />
<glyph unicode="&#xf8;" horiz-adv-x="786" d="M20 0v37h72v833h-72v37h236v-37h-49v-833h129v833h-49v37h213v-37h-49v-833h129v833h-50v37h236v-37h-72v-833h72v-37h-746z" />
<glyph unicode="&#x448;" horiz-adv-x="786" d="M20 0v37h72v833h-72v37h236v-37h-49v-833h129v833h-49v37h213v-37h-49v-833h129v833h-50v37h236v-37h-72v-833h72v-37h-746z" />
<glyph unicode="&#xf9;" horiz-adv-x="786" d="M20 0v37h72v833h-72v37h236v-37h-49v-833h129v833h-49v37h213v-37h-49v-833h129v833h-50v37h236v-37h-72v-833h62v-336h-37q0 160 -14 213q-23 86 -97 86h-588z" />
<glyph unicode="&#x449;" horiz-adv-x="786" d="M20 0v37h72v833h-72v37h236v-37h-49v-833h129v833h-49v37h213v-37h-49v-833h129v833h-50v37h236v-37h-72v-833h62v-336h-37q0 160 -14 213q-23 86 -97 86h-588z" />
<glyph unicode="&#xfa;" horiz-adv-x="501" d="M-82 1122v336h361v-37h-72v-889h51q106 0 160 -77q47 -68 47 -187q0 -109 -33 -170q-53 -98 -188 -98h-224v37h72v1384h-26q-72 0 -91.5 -73.5t-19.5 -225.5h-37zM207 37h41q59 0 82 76q16 55 16 155q0 102 -22.5 165t-75.5 63h-41v-459z" />
<glyph unicode="&#x44a;" horiz-adv-x="501" d="M-82 1122v336h361v-37h-72v-889h51q106 0 160 -77q47 -68 47 -187q0 -109 -33 -170q-53 -98 -188 -98h-224v37h72v1384h-26q-72 0 -91.5 -73.5t-19.5 -225.5h-37zM207 37h41q59 0 82 76q16 55 16 155q0 102 -22.5 165t-75.5 63h-41v-459z" />
<glyph unicode="&#xfb;" horiz-adv-x="743" d="M20 0v37h72v833h-72v37h259v-37h-72v-338h51q106 0 160 -77q47 -68 47 -187q0 -109 -33 -170q-53 -98 -188 -98h-224zM207 37h41q59 0 82 76q16 55 16 155q0 102 -22.5 165t-75.5 63h-41v-459zM465 0v37h72v833h-72v37h258v-37h-72v-833h72v-37h-258z" />
<glyph unicode="&#x44b;" horiz-adv-x="743" d="M20 0v37h72v833h-72v37h259v-37h-72v-338h51q106 0 160 -77q47 -68 47 -187q0 -109 -33 -170q-53 -98 -188 -98h-224zM207 37h41q59 0 82 76q16 55 16 155q0 102 -22.5 165t-75.5 63h-41v-459zM465 0v37h72v833h-72v37h258v-37h-72v-833h72v-37h-258z" />
<glyph unicode="&#xfc;" horiz-adv-x="501" d="M20 0v37h72v833h-72v37h259v-37h-72v-338h51q106 0 160 -77q47 -68 47 -187q0 -109 -33 -170q-53 -98 -188 -98h-224zM207 37h41q59 0 82 76q16 55 16 155q0 102 -22.5 165t-75.5 63h-41v-459z" />
<glyph unicode="&#x44c;" horiz-adv-x="501" d="M20 0v37h72v833h-72v37h259v-37h-72v-338h51q106 0 160 -77q47 -68 47 -187q0 -109 -33 -170q-53 -98 -188 -98h-224zM207 37h41q59 0 82 76q16 55 16 155q0 102 -22.5 165t-75.5 63h-41v-459z" />
<glyph unicode="&#xfd;" horiz-adv-x="385" d="M41 379h37q0 -166 24.5 -254t71.5 -88q55 0 55 115v315h-118v37h118v178q0 106 -17 153.5t-48 47.5q-33 0 -59.5 -88t-26.5 -211h-37v336h37q0 -25 18 -25q8 0 31 12.5t41 12.5q88 0 139 -179q41 -143 41 -307q0 -190 -33 -307q-39 -139 -118 -139q-90 0 -123 97t-33 294 z" />
<glyph unicode="&#x44d;" horiz-adv-x="385" d="M41 379h37q0 -166 24.5 -254t71.5 -88q55 0 55 115v315h-118v37h118v178q0 106 -17 153.5t-48 47.5q-33 0 -59.5 -88t-26.5 -211h-37v336h37q0 -25 18 -25q8 0 31 12.5t41 12.5q88 0 139 -179q41 -143 41 -307q0 -190 -33 -307q-39 -139 -118 -139q-90 0 -123 97t-33 294 z" />
<glyph unicode="&#xfe;" horiz-adv-x="679" d="M10 0v37h62v1409h-62v37h176v-979h80q0 172 39 280q49 135 148 136q102 0 149 -148q37 -117 37 -303q0 -193 -35 -313q-49 -168 -151 -168q-98 0 -148 166q-39 131 -39 313h-80v-430h62v-37h-238zM385 182q0 -72 8 -100q16 -57 60 -57q49 0 61 81q6 39 6 78v496 q0 84 -10 129q-16 74 -57 74q-47 0 -62 -105q-6 -47 -6 -98v-498z" />
<glyph unicode="&#x44e;" horiz-adv-x="679" d="M10 0v37h62v1409h-62v37h176v-979h80q0 172 39 280q49 135 148 136q102 0 149 -148q37 -117 37 -303q0 -193 -35 -313q-49 -168 -151 -168q-98 0 -148 166q-39 131 -39 313h-80v-430h62v-37h-238zM385 182q0 -72 8 -100q16 -57 60 -57q49 0 61 81q6 39 6 78v496 q0 84 -10 129q-16 74 -57 74q-47 0 -62 -105q-6 -47 -6 -98v-498z" />
<glyph unicode="&#xff;" horiz-adv-x="559" d="M0 0v37h72l118 379q-119 55 -118 239q0 115 62.5 183.5t180.5 68.5h224v-37h-72v-833h72v-37h-258v37h71v30BFCEDCA07" />
<glyph unicode="&#x44f;" horiz-adv-x="559" d="M0 0v37h72l118 379q-119 55 -118 239q0 115 62.5 183.5t180.5 68.5h224v-37h-72v-833h72v-37h-258v37h71v30BFCEDCA07" />
<glyph unicode="&#x192;" horiz-adv-x="307" d="M-184 -428q0 51 31.5 85t76.5 34q27 0 46.5 -19.5t19.5 -48.5t-17.5 -50.5t-42.5 -21.5q-8 0 -24.5 6.5t-2052B348A81" />
<glyph unicode="&#x453;" horiz-adv-x="307" d="M-184 -428q0 51 31.5 85t76.5 34q27 0 46.5 -19.5t19.5 -48.5t-17.5 -50.5t-42.5 -21.5q-8 0 -24.5 6.5t-2052B348A81" />
<glyph unicode="&#x2c6;" horiz-adv-x="636" d="M20 446l267 461h63l266 -461l-47 -26l-250 432l-251 -432z" />
<glyph unicode="&#x2da;" horiz-adv-x="368" d="M-287 410q0 117 84 203t203 86t203 -84t84 -205q0 -119 -84 -203t-203 -84t-203 84t-84 203zM-250 410q0 -102 74 -176t176 -74t176 74t74 176t-72.5 177t-177.5 75q-102 0 -176 -74t-74 -178z" />
<glyph unicode="&#x2dc;" horiz-adv-x="368" d="M-246 123q0 66 41 110.5t102 44.5q33 0 135 -35q53 -18 82 -18q39 0 67 15.5t28 37.5h36q0 -156 -178 -155q-29 0 -75 16q-106 37 -132 37q-29 0 -49 -13.5t-20 -39.5h-37z" />
<glyph unicode="&#x400;" horiz-adv-x="524" d="M146 1729q0 70 46 126t112 56q10 0 10 -14q0 -18 -10 -19q-31 0 -72 -38.5t-41 -71.5q0 -35 16 -35q8 0 28.5 8t27.5 8q59 0 59 -61q0 -33 -20.5 -57.5t-51.5 -24.5q-47 0 -75.5 35t-28.5 88zM20 0v37h99v1384h-84v37h428v-430h-37q0 166 -14 248q-27 145 -97 145h-73 v-659h41q49 0 65.5 67.5t16.5 194.5h36v-561h-36q0 135 -13 186q-18 76 -69 76h-41v-688h63q141 0 141 461h37v-498h-463z" />
<glyph unicode="&#x40d;" horiz-adv-x="638" d="M223 1729q0 70 46 126t112 56q10 0 10 -14q0 -18 -10 -19q-31 0 -72 -38.5t-41 -71.5q0 -35 16 -35q8 0 28.5 8t27.5 8q59 0 59 -61q0 -33 -20.5 -57.5t-51.5 -24.5q-47 0 -75.5 35t-28.5 88zM20 0v37h99v1384h-84v37h268v-37h-61v-1026l155 920v106h-61v37h282v-37h-98 v-1384h98v-37h-282v37h61v1053l-155 -922v-131h61v-37h-283z" />
<glyph unicode="&#x450;" horiz-adv-x="421" d="M121 1165q0 70 46 126t112 56q10 0 10 -14q0 -18 -10 -19q-31 0 -72 -38.5t-41 -71.5q0 -35 16 -35q8 0 280D17919AC6" />
<glyph unicode="&#x45d;" horiz-adv-x="542" d="M166 1165q0 70 46 126t112 56q10 0 10 -14q0 -18 -10 -19q-31 0 -72 -38.5t-41 -71.5q0 -35 16 -35q8 0 28.5 8t27.5 8q59 0 59 -61q0 -33 -20.5 -57.5t-51.5 -24.5q-47 0 -75.5 35t-28.5 88zM20 0v37h72v833h-72v37h236v-37h-49v-616l129 594v22h-49v37h235v-37h-71 v-833h71v-37h-235v37h49v633l-129 -590v-43h49v-37h-236z" />
<glyph unicode="&#x4ae;" horiz-adv-x="530" d="M29 1421v37h241v-37h-61l102 -700l99 700h-62v37h182v-37h-79l-109 -807v-577h98v-37h-319v37h98v557l-129 827h-61z" />
<glyph unicode="&#x4c0;" horiz-adv-x="360" d="M20 0v37h99v1384h-99v37h320v-37h-98v-1384h98v-37h-320z" />
<glyph unicode="&#x2000;" horiz-adv-x="954" />
<glyph unicode="&#x2001;" horiz-adv-x="1910" />
<glyph unicode="&#x2002;" horiz-adv-x="954" />
<glyph unicode="&#x2003;" horiz-adv-x="1910" />
<glyph unicode="&#x2004;" horiz-adv-x="636" />
<glyph unicode="&#x2005;" horiz-adv-x="477" />
<glyph unicode="&#x2006;" horiz-adv-x="317" />
<glyph unicode="&#x2007;" horiz-adv-x="317" />
<glyph unicode="&#x2008;" horiz-adv-x="237" />
<glyph unicode="&#x2009;" horiz-adv-x="380" />
<glyph unicode="&#x200a;" horiz-adv-x="104" />
<glyph unicode="&#x2010;" horiz-adv-x="325" d="M41 508v86h244v-86h-244z" />
<glyph unicode="&#x2011;" horiz-adv-x="325" d="M41 508v86h244v-86h-244z" />
<glyph unicode="&#x2012;" horiz-adv-x="325" d="M41 508v86h244v-86h-244z" />
<glyph unicode="&#x2013;" horiz-adv-x="573" d="M41 508v45h491v-45h-491z" />
<glyph unicode="&#x2014;" horiz-adv-x="983" d="M41 508v45h901v-45h-901z" />
<glyph unicode="&#x2018;" horiz-adv-x="258" d="M41 1276q0 70 46 126t112 56q10 0 10 -14q0 -18 -10 -19q-31 0 -72 -38.5t-41 -71.5q0 -35 16 -35q8 0 29 00284FEA55" />
<glyph unicode="&#x2019;" horiz-adv-x="258" d="M41 1376q0 33 20.5 57.5t51.5 24.5q47 0 75.5 -34.5t28.5 -88.5q0 -70 -46 -126t-112 -56q-10 0 -10 14q0 18 10 19q31 0 72 39t41 71q0 35 -16 35q-8 0 -24.5 -12t-31.5 -12q-27 0 -43 20t-16 49z" />
<glyph unicode="&#x201a;" horiz-adv-x="301" d="M39 45q0 33 20.5 57.5t51.5 24.5q47 0 75.5 -35t28.5 -88q0 -70 -46 -126t-112 -56q-10 0 -10 14q0 18 10 0627E0AA5B" />
<glyph unicode="&#x201c;" horiz-adv-x="475" d="M41 1276q0 70 46 126t112 56q10 0 10 -14q0 -18 -10 -19q-31 0 -72 -38.5t-41 -71.5q0 -35 16 -35q8 0 29 02AD4D3A4C" />
<glyph unicode="&#x201d;" horiz-adv-x="475" d="M41 1376q0 33 20.5 57.5t51.5 24.5q47 0 75.5 -34.5t28.5 -88.5q0 -70 -46 -126t-112 -56q-10 0 -10 14q0 18 10 19q31 0 72 39t41 71q0 35 -16 35q-8 0 -24.5 -12t-31.5 -12q-27 0 -43 20t-16 49zM258 1376q0 33 20.5 57.5t51.5 24.5q47 0 75.5 -34.5t28.5 -88.5 q0 -70 -46 -126t-112 -56q-10 0 -10 14q0 18 10 19q31 0 72 39t41 71q0 35 -16 35q-8 0 -24.5 -12t-31.5 -12q-27 0 -43 20t-16 49z" />
<glyph unicode="&#x201e;" horiz-adv-x="475" d="M41 45q0 33 20.5 57.5t51.5 24.5q47 0 75.5 -35t28.5 -88q0 -70 -46 -126t-112 -56q-10 0 -10 14q0 18 10 032313DA86" />
<glyph unicode="&#x2022;" horiz-adv-x="323" d="M41 561q0 49 36 85t85 36t85 -36t36 -85t-36 -85t-85 -36t-85 36t-36 85z" />
<glyph unicode="&#x2026;" horiz-adv-x="700" d="M41 51q0 31 22.5 53.5t53.5 22.5t53.5 -22.5t22.5 -53.5t-23 -53.5t-53 -22.5q-31 0 -53.5 22.5t-22.5 53.09350A8AEC" />
<glyph unicode="&#x202f;" horiz-adv-x="380" />
<glyph unicode="&#x2039;" horiz-adv-x="280" d="M41 225v64l164 219l35 -29l-144 -221l144 -225l-35 -33z" />
<glyph unicode="&#x203a;" horiz-adv-x="280" d="M41 33l35 -33l164 225v64l-164 219l-35 -29l143 -221z" />
<glyph unicode="&#x205f;" horiz-adv-x="477" />
<glyph unicode="&#x2122;" horiz-adv-x="1155" d="M41 1202v219h381v-219h-37q0 94 -12 129q-18 53 -78 53h-14v-557h79v-36h-256v36h78v557h-16q-57 0 -72.5 -45t-15.5 -137h-37zM463 791v36h80v557h-80v37h182l158 -411l133 411h178v-37h-80v-557h80v-36h-256v36h78v461l-158 -461h-20l-176 476l-2 -476h77v-36h-194z " />
<glyph unicode="&#xe000;" horiz-adv-x="905" d="M0 905h905v-905h-905v905z" />
</font>
</defs></svg> 